[
  {
    "place": "Brussels",
    "appointment": "yes",
    "free": "no",
    "day": "Tuesday",
    "daypart": "afternoon",
    "hour": "13h30 - 16h",
    "organisation": "S-Clinic",
    "address": "Rue des Alexiens 13, 1000 Brussels",
    "telephone": "02 535 37 32",
    "email": "",
    "website": "https://www.stpierre-bru.be/fr/consultations/prendre-un-rendez-vous",
    "startTime": "2021-07-27T11:30:10.354Z",
    "endTime": "2021-07-27T14:00:10.356Z"
  },
  {
    "place": "Brussels",
    "appointment": "yes",
    "free": "no",
    "day": "Friday",
    "daypart": "morning",
    "hour": "8h30 - 11h",
    "organisation": "S-Clinic",
    "address": "Rue des Alexiens 13, 1000 Brussels",
    "telephone": "02 535 37 32",
    "email": "",
    "website": "https://www.stpierre-bru.be/fr/consultations/prendre-un-rendez-vous",
    "startTime": "2021-07-30T06:30:10.357Z",
    "endTime": "2021-07-30T09:00:10.357Z"
  },
  {
    "place": "Brussels",
    "appointment": "yes",
    "free": "no",
    "day": "Saturday",
    "daypart": "afternoon",
    "hour": "13h30 - 15h30",
    "organisation": "S-Clinic",
    "address": "Rue des Alexiens 13, 1000 Brussels",
    "telephone": "02 535 37 32",
    "email": "",
    "website": "https://www.stpierre-bru.be/fr/consultations/prendre-un-rendez-vous",
    "startTime": "2021-07-31T11:30:10.357Z",
    "endTime": "2021-07-31T13:30:10.357Z"
  },
  {
    "place": "Brussels",
    "appointment": "yes",
    "free": "no",
    "day": "Monday",
    "daypart": "morning",
    "hour": "9h - 12h",
    "organisation": "Elisa Centre",
    "address": "Cellebroersstraat 11, 1000 Brussels",
    "telephone": "02 535 30 03",
    "email": "",
    "website": "https://www.stpierre-bru.be/nl/raadplegingen/een-afspraak-maken",
    "startTime": "2021-07-26T07:00:10.358Z",
    "endTime": "2021-07-26T10:00:10.358Z"
  },
  {
    "place": "Brussels",
    "appointment": "yes",
    "free": "no",
    "day": "Monday",
    "daypart": "afternoon",
    "hour": "13h - 17h",
    "organisation": "Elisa Centre",
    "address": "Cellebroersstraat 11, 1000 Brussels",
    "telephone": "02 535 30 03",
    "email": "",
    "website": "https://www.stpierre-bru.be/nl/raadplegingen/een-afspraak-maken",
    "startTime": "2021-07-26T11:00:10.358Z",
    "endTime": "2021-07-26T15:00:10.358Z"
  },
  {
    "place": "Brussels",
    "appointment": "yes",
    "free": "no",
    "day": "Wednesday",
    "daypart": "afternoon",
    "hour": "13h - 17h",
    "organisation": "Elisa Centre",
    "address": "Cellebroersstraat 11, 1000 Brussels",
    "telephone": "02 535 30 03",
    "email": "",
    "website": "https://www.stpierre-bru.be/nl/raadplegingen/een-afspraak-maken",
    "startTime": "2021-07-28T11:00:10.358Z",
    "endTime": "2021-07-28T15:00:10.358Z"
  },
  {
    "place": "Brussels",
    "appointment": "no",
    "free": "no",
    "day": "Monday",
    "daypart": "afternoon",
    "hour": "15u30 - 17h30",
    "organisation": "UCL Saint-Luc",
    "address": "Hippocrateslaan 10, 1200 Brussels",
    "telephone": "02 764 19 02",
    "email": "",
    "website": "",
    "startTime": "2021-07-26T12:14:10.358Z",
    "endTime": "2021-07-26T15:30:10.358Z"
  },
  {
    "place": "Brussels",
    "appointment": "no",
    "free": "no",
    "day": "Wednesday",
    "daypart": "morning",
    "hour": "11h - 13h",
    "organisation": "UCL Saint-Luc",
    "address": "Hippocrateslaan 10, 1200 Brussels",
    "telephone": "02 764 19 02",
    "email": "",
    "website": "",
    "startTime": "2021-07-28T09:00:10.358Z",
    "endTime": "2021-07-28T11:00:10.358Z"
  },
  {
    "place": "Brussels",
    "appointment": "yes",
    "free": "no",
    "day": "Monday",
    "daypart": "morning",
    "hour": "9h - 12h",
    "organisation": "Erasmusziekenhuis",
    "address": "Lenniksebaan 808, 1070 Brussels",
    "telephone": "02 555 4688",
    "email": "CRSida@erasme.ulb.ac.be",
    "website": "https://www.erasme.ulb.ac.be/fr/services-de-soins/services-multidisciplinaires/centre-de-reference-sida",
    "startTime": "2021-07-26T07:00:10.358Z",
    "endTime": "2021-07-26T10:00:10.359Z"
  },
  {
    "place": "Brussels",
    "appointment": "yes",
    "free": "no",
    "day": "Tuesday",
    "daypart": "morning",
    "hour": "9h - 12h",
    "organisation": "Erasmusziekenhuis",
    "address": "Lenniksebaan 808, 1070 Brussels",
    "telephone": "02 555 4688",
    "email": "CRSida@erasme.ulb.ac.be",
    "website": "https://www.erasme.ulb.ac.be/fr/services-de-soins/services-multidisciplinaires/centre-de-reference-sida",
    "startTime": "2021-07-27T07:00:10.359Z",
    "endTime": "2021-07-27T10:00:10.359Z"
  },
  {
    "place": "Brussels",
    "appointment": "yes",
    "free": "no",
    "day": "Wednesday",
    "daypart": "morning",
    "hour": "9h - 12h",
    "organisation": "Erasmusziekenhuis",
    "address": "Lenniksebaan 808, 1070 Brussels",
    "telephone": "02 555 4688",
    "email": "CRSida@erasme.ulb.ac.be",
    "website": "https://www.erasme.ulb.ac.be/fr/services-de-soins/services-multidisciplinaires/centre-de-reference-sida",
    "startTime": "2021-07-28T07:00:10.359Z",
    "endTime": "2021-07-28T10:00:10.359Z"
  },
  {
    "place": "Brussels",
    "appointment": "yes",
    "free": "no",
    "day": "Thursday",
    "daypart": "morning",
    "hour": "9h - 12h",
    "organisation": "Erasmusziekenhuis",
    "address": "Lenniksebaan 808, 1070 Brussels",
    "telephone": "02 555 4688",
    "email": "CRSida@erasme.ulb.ac.be",
    "website": "https://www.erasme.ulb.ac.be/fr/services-de-soins/services-multidisciplinaires/centre-de-reference-sida",
    "startTime": "2021-07-29T07:00:10.359Z",
    "endTime": "2021-07-29T10:00:10.359Z"
  },
  {
    "place": "Brussels",
    "appointment": "yes",
    "free": "no",
    "day": "Friday",
    "daypart": "morning",
    "hour": "9h - 12h",
    "organisation": "Erasmusziekenhuis",
    "address": "Lenniksebaan 808, 1070 Brussels",
    "telephone": "02 555 4688",
    "email": "CRSida@erasme.ulb.ac.be",
    "website": "https://www.erasme.ulb.ac.be/fr/services-de-soins/services-multidisciplinaires/centre-de-reference-sida",
    "startTime": "2021-07-30T07:00:10.359Z",
    "endTime": "2021-07-30T10:00:10.359Z"
  },
  {
    "place": "Brussels",
    "appointment": "yes",
    "free": "no",
    "day": "Monday",
    "daypart": "afternoon",
    "hour": "13h - 17h",
    "organisation": "Erasmusziekenhuis",
    "address": "Lenniksebaan 808, 1070 Brussels",
    "telephone": "02 555 4688",
    "email": "CRSida@erasme.ulb.ac.be",
    "website": "https://www.erasme.ulb.ac.be/fr/services-de-soins/services-multidisciplinaires/centre-de-reference-sida",
    "startTime": "2021-07-26T11:00:10.359Z",
    "endTime": "2021-07-26T15:00:10.359Z"
  },
  {
    "place": "Brussels",
    "appointment": "yes",
    "free": "no",
    "day": "Tuesday",
    "daypart": "afternoon",
    "hour": "13h - 17h",
    "organisation": "Erasmusziekenhuis",
    "address": "Lenniksebaan 808, 1070 Brussels",
    "telephone": "02 555 4688",
    "email": "CRSida@erasme.ulb.ac.be",
    "website": "https://www.erasme.ulb.ac.be/fr/services-de-soins/services-multidisciplinaires/centre-de-reference-sida",
    "startTime": "2021-07-27T11:00:10.359Z",
    "endTime": "2021-07-27T15:00:10.360Z"
  },
  {
    "place": "Brussels",
    "appointment": "yes",
    "free": "no",
    "day": "Wednesday",
    "daypart": "afternoon",
    "hour": "13h - 17h",
    "organisation": "Erasmusziekenhuis",
    "address": "Lenniksebaan 808, 1070 Brussels",
    "telephone": "02 555 4688",
    "email": "CRSida@erasme.ulb.ac.be",
    "website": "https://www.erasme.ulb.ac.be/fr/services-de-soins/services-multidisciplinaires/centre-de-reference-sida",
    "startTime": "2021-07-28T11:00:10.360Z",
    "endTime": "2021-07-28T15:00:10.360Z"
  },
  {
    "place": "Brussels",
    "appointment": "yes",
    "free": "no",
    "day": "Thursday",
    "daypart": "afternoon",
    "hour": "13h - 17h",
    "organisation": "Erasmusziekenhuis",
    "address": "Lenniksebaan 808, 1070 Brussels",
    "telephone": "02 555 4688",
    "email": "CRSida@erasme.ulb.ac.be",
    "website": "https://www.erasme.ulb.ac.be/fr/services-de-soins/services-multidisciplinaires/centre-de-reference-sida",
    "startTime": "2021-07-29T11:00:10.360Z",
    "endTime": "2021-07-29T15:00:10.360Z"
  },
  {
    "place": "Brussels",
    "appointment": "yes",
    "free": "no",
    "day": "Friday",
    "daypart": "afternoon",
    "hour": "13h - 17h",
    "organisation": "Erasmusziekenhuis",
    "address": "Lenniksebaan 808, 1070 Brussels",
    "telephone": "02 555 4688",
    "email": "CRSida@erasme.ulb.ac.be",
    "website": "https://www.erasme.ulb.ac.be/fr/services-de-soins/services-multidisciplinaires/centre-de-reference-sida",
    "startTime": "2021-07-30T11:00:10.360Z",
    "endTime": "2021-07-30T15:00:10.360Z"
  },
  {
    "place": "Brussels",
    "appointment": "yes",
    "free": "no",
    "day": "Thursday",
    "daypart": "morning",
    "hour": "8h - 12h",
    "organisation": "ARC UZ VUB Brussels",
    "address": "Laarbeeklaan 101, 1090 Brussels",
    "telephone": "02 477 60 12",
    "email": "afspraak_dermatologie@uzBrussels.be",
    "website": "https://www.uzBrussels.be/web/dermatologie/in-het-uz-Brussels",
    "startTime": "2021-07-29T06:00:10.360Z",
    "endTime": "2021-07-29T10:00:10.360Z"
  },
  {
    "place": "Brussels",
    "appointment": "no",
    "free": "yes",
    "day": "Wednesday",
    "daypart": "afternoon",
    "hour": "19h - 21h30",
    "organisation": "ex æquo",
    "address": "Steenstraat 29, 1000 Brussels",
    "telephone": "02 736 28 61",
    "email": "info@exaequo.be",
    "website": "www.exaequo.be",
    "startTime": "2021-07-28T17:00:10.360Z",
    "endTime": "2021-07-28T19:30:10.360Z"
  },
  {
    "place": "Brussels",
    "appointment": "no",
    "free": "yes",
    "day": "Thursday",
    "daypart": "afternoon",
    "hour": "19h - 21h30",
    "organisation": "ex æquo",
    "address": "Steenstraat 29, 1000 Brussels",
    "telephone": "02 736 28 61",
    "email": "info@exaequo.be",
    "website": "www.exaequo.be",
    "startTime": "2021-07-29T17:00:10.361Z",
    "endTime": "2021-07-29T19:30:10.361Z"
  },
  {
    "place": "Brussels",
    "appointment": "yes",
    "free": "yes",
    "day": "Monday",
    "daypart": "morning",
    "hour": "10h - 12h30",
    "organisation": "ex æquo",
    "address": "Steenstraat 29, 1000 Brussels",
    "telephone": "02 736 28 61",
    "email": "info@exaequo.be",
    "website": "www.exaequo.be",
    "startTime": "2021-07-26T08:00:10.361Z",
    "endTime": "2021-07-26T10:30:10.361Z"
  },
  {
    "place": "Brussels",
    "appointment": "yes",
    "free": "yes",
    "day": "Monday",
    "daypart": "afternoon",
    "hour": "13h - 17h",
    "organisation": "ex æquo",
    "address": "Steenstraat 29, 1000 Brussels",
    "telephone": "02 736 28 61",
    "email": "info@exaequo.be",
    "website": "www.exaequo.be",
    "startTime": "2021-07-26T11:00:10.361Z",
    "endTime": "2021-07-26T15:00:10.361Z"
  },
  {
    "place": "Brussels",
    "appointment": "yes",
    "free": "yes",
    "day": "Tuesday",
    "daypart": "morning",
    "hour": "10h - 12h30",
    "organisation": "ex æquo",
    "address": "Steenstraat 29, 1000 Brussels",
    "telephone": "02 736 28 61",
    "email": "info@exaequo.be",
    "website": "www.exaequo.be",
    "startTime": "2021-07-27T08:00:10.361Z",
    "endTime": "2021-07-27T10:30:10.361Z"
  },
  {
    "place": "Brussels",
    "appointment": "yes",
    "free": "yes",
    "day": "Tuesday",
    "daypart": "afternoon",
    "hour": "13h - 17h",
    "organisation": "ex æquo",
    "address": "Steenstraat 29, 1000 Brussels",
    "telephone": "02 736 28 61",
    "email": "info@exaequo.be",
    "website": "www.exaequo.be",
    "startTime": "2021-07-27T11:00:10.361Z",
    "endTime": "2021-07-27T15:00:10.361Z"
  },
  {
    "place": "Brussels",
    "appointment": "yes",
    "free": "yes",
    "day": "Wednesday",
    "daypart": "morning",
    "hour": "10h - 12h30",
    "organisation": "ex æquo",
    "address": "Steenstraat 29, 1000 Brussels",
    "telephone": "02 736 28 61",
    "email": "info@exaequo.be",
    "website": "www.exaequo.be",
    "startTime": "2021-07-28T08:00:10.361Z",
    "endTime": "2021-07-28T10:30:10.361Z"
  },
  {
    "place": "Brussels",
    "appointment": "yes",
    "free": "yes",
    "day": "Wednesday",
    "daypart": "afternoon",
    "hour": "13h - 17h",
    "organisation": "ex æquo",
    "address": "Steenstraat 29, 1000 Brussels",
    "telephone": "02 736 28 61",
    "email": "info@exaequo.be",
    "website": "www.exaequo.be",
    "startTime": "2021-07-28T11:00:10.361Z",
    "endTime": "2021-07-28T15:00:10.361Z"
  },
  {
    "place": "Brussels",
    "appointment": "yes",
    "free": "yes",
    "day": "Thursday",
    "daypart": "morning",
    "hour": "10h - 12h30",
    "organisation": "ex æquo",
    "address": "Steenstraat 29, 1000 Brussels",
    "telephone": "02 736 28 61",
    "email": "info@exaequo.be",
    "website": "www.exaequo.be",
    "startTime": "2021-07-29T08:00:10.361Z",
    "endTime": "2021-07-29T10:30:10.362Z"
  },
  {
    "place": "Brussels",
    "appointment": "yes",
    "free": "yes",
    "day": "Thursday",
    "daypart": "afternoon",
    "hour": "13h - 17h",
    "organisation": "ex æquo",
    "address": "Steenstraat 29, 1000 Brussels",
    "telephone": "02 736 28 61",
    "email": "info@exaequo.be",
    "website": "www.exaequo.be",
    "startTime": "2021-07-29T11:00:10.362Z",
    "endTime": "2021-07-29T15:00:10.362Z"
  },
  {
    "place": "Brussels",
    "appointment": "yes",
    "free": "yes",
    "day": "Friday",
    "daypart": "morning",
    "hour": "10h - 12h30",
    "organisation": "ex æquo",
    "address": "Steenstraat 29, 1000 Brussels",
    "telephone": "02 736 28 61",
    "email": "info@exaequo.be",
    "website": "www.exaequo.be",
    "startTime": "2021-07-30T08:00:10.363Z",
    "endTime": "2021-07-30T10:30:10.363Z"
  },
  {
    "place": "Brussels",
    "appointment": "yes",
    "free": "yes",
    "day": "Friday",
    "daypart": "afternoon",
    "hour": "13h - 17h",
    "organisation": "ex æquo",
    "address": "Steenstraat 29, 1000 Brussels",
    "telephone": "02 736 28 61",
    "email": "info@exaequo.be",
    "website": "www.exaequo.be",
    "startTime": "2021-07-30T11:00:10.363Z",
    "endTime": "2021-07-30T15:00:10.364Z"
  },
  {
    "place": "Brussels",
    "appointment": "no",
    "free": "no",
    "day": "Monday",
    "daypart": "morning",
    "hour": "8h - 13h",
    "organisation": "Elisa Centre",
    "address": "Cellebroersstraat 11, 1000 Brussels",
    "telephone": "02 535 30 03",
    "email": "",
    "website": "",
    "startTime": "2021-07-26T06:00:10.364Z",
    "endTime": "2021-07-26T11:00:10.364Z"
  },
  {
    "place": "Brussels",
    "appointment": "no",
    "free": "no",
    "day": "Wednesday",
    "daypart": "afternoon",
    "hour": "12h15 - 15h",
    "organisation": "Elisa Centre (age 15 - 29)",
    "address": "Cellebroersstraat 11, 1000 Brussels",
    "telephone": "02 535 30 03",
    "email": "",
    "website": "",
    "startTime": "2021-07-28T10:15:10.364Z",
    "endTime": "2021-07-28T13:00:10.364Z"
  },
  {
    "place": "Brussels",
    "appointment": "no",
    "free": "no",
    "day": "Thursday",
    "daypart": "afternoon",
    "hour": "15h30 - 19h",
    "organisation": "Elisa Centre",
    "address": "Cellebroersstraat 11, 1000 Brussels",
    "telephone": "02 535 30 03",
    "email": "",
    "website": "",
    "startTime": "2021-07-29T13:30:10.364Z",
    "endTime": "2021-07-29T17:00:10.364Z"
  },
  {
    "place": "Brussels",
    "appointment": "no",
    "free": "no",
    "day": "Tuesday",
    "daypart": "afternoon",
    "hour": "13h30 - 16h",
    "organisation": "S-Clinic",
    "address": "Rue des Alexiens 13, 1000 Brussels",
    "telephone": "",
    "email": "",
    "website": "",
    "startTime": "2021-07-27T11:30:10.364Z",
    "endTime": "2021-07-27T14:00:10.364Z"
  },
  {
    "place": "Brussels",
    "appointment": "no",
    "free": "no",
    "day": "Friday",
    "daypart": "morning",
    "hour": "8h30 - 11h",
    "organisation": "S-Clinic",
    "address": "Rue des Alexiens 13, 1000 Brussels",
    "telephone": "",
    "email": "",
    "website": "",
    "startTime": "2021-07-30T06:30:10.364Z",
    "endTime": "2021-07-30T09:00:10.364Z"
  },
  {
    "place": "Brussels",
    "appointment": "no",
    "free": "no",
    "day": "Friday",
    "daypart": "afternoon",
    "hour": "13h30 - 15h30",
    "organisation": "S-Clinic",
    "address": "Rue des Alexiens 13, 1000 Brussels",
    "telephone": "",
    "email": "",
    "website": "",
    "startTime": "2021-07-30T11:30:10.364Z",
    "endTime": "2021-07-30T13:30:10.364Z"
  },
  {
    "place": "Brussels",
    "appointment": "no",
    "free": "no",
    "day": "Monday",
    "daypart": "afternoon",
    "hour": "15u30 - 17h30",
    "organisation": "UCL Saint-Luc",
    "address": "Hippocrateslaan 10, 1200 Brussels",
    "telephone": "02 764 19 02",
    "email": "",
    "website": "",
    "startTime": "2021-07-26T12:14:10.365Z",
    "endTime": "2021-07-26T15:30:10.365Z"
  },
  {
    "place": "Brussels",
    "appointment": "no",
    "free": "no",
    "day": "Wednesday",
    "daypart": "morning",
    "hour": "11h - 13h",
    "organisation": "UCL Saint-Luc",
    "address": "Hippocrateslaan 10, 1200 Brussels",
    "telephone": "02 764 19 02",
    "email": "",
    "website": "",
    "startTime": "2021-07-28T09:00:10.365Z",
    "endTime": "2021-07-28T11:00:10.365Z"
  },
  {
    "place": "Brussels",
    "appointment": "no",
    "free": "yes",
    "day": "Monday",
    "daypart": "afternoon",
    "hour": "14h - 16h",
    "organisation": "CPF Yser Aimer Jeunes",
    "address": "Rue Saint-Jean Népomucène 28, 1000 Brusselss",
    "telephone": "02 511 32 20",
    "email": "",
    "website": "",
    "startTime": "2021-07-26T12:00:10.365Z",
    "endTime": "2021-07-26T14:00:10.365Z"
  },
  {
    "place": "Brussels",
    "appointment": "no",
    "free": "yes",
    "day": "Tuesday",
    "daypart": "afternoon",
    "hour": "17h - 19h",
    "organisation": "CPF Jette",
    "address": "Rue Léon Théodor 108, 1090 Brussels",
    "telephone": "02 426 06 27",
    "email": "",
    "website": "",
    "startTime": "2021-07-27T15:00:10.365Z",
    "endTime": "2021-07-27T17:00:10.365Z"
  },
  {
    "place": "Brussels",
    "appointment": "no",
    "free": "yes",
    "day": "Monday",
    "daypart": "afternoon",
    "hour": "14h - 16h",
    "organisation": "CPF Aimer Jeunes",
    "address": "Rue Saint-Jean Népomucène 28, 1000 Brusselss",
    "telephone": "02 511 32 20",
    "email": "",
    "website": "http://aimer-jeunes.be/?Aimer-Jeunes-a-Madrid",
    "startTime": "2021-07-26T12:00:10.365Z",
    "endTime": "2021-07-26T14:00:10.365Z"
  },
  {
    "place": "Brussels",
    "appointment": "no",
    "free": "yes",
    "day": "Monday",
    "daypart": "morning",
    "hour": "9h - 12h",
    "organisation": "CPF Marolles",
    "address": "Rue de la Roue 21, 1000 Brusselss",
    "telephone": "02 426 06 27",
    "email": "",
    "website": "",
    "startTime": "2021-07-26T07:00:10.365Z",
    "endTime": "2021-07-26T10:00:10.365Z"
  },
  {
    "place": "Brussels",
    "appointment": "no",
    "free": "yes",
    "day": "Tuesday",
    "daypart": "morning",
    "hour": "9h - 12h",
    "organisation": "CPF Marolles",
    "address": "Rue de la Roue 21, 1000 Brusselss",
    "telephone": "02 426 06 27",
    "email": "",
    "website": "",
    "startTime": "2021-07-27T07:00:10.365Z",
    "endTime": "2021-07-27T10:00:10.365Z"
  },
  {
    "place": "Brussels",
    "appointment": "no",
    "free": "yes",
    "day": "Wednesday",
    "daypart": "morning",
    "hour": "9h - 12h",
    "organisation": "CPF Marolles",
    "address": "Rue de la Roue 21, 1000 Brusselss",
    "telephone": "02 426 06 27",
    "email": "",
    "website": "",
    "startTime": "2021-07-28T07:00:10.365Z",
    "endTime": "2021-07-28T10:00:10.365Z"
  },
  {
    "place": "Brussels",
    "appointment": "no",
    "free": "yes",
    "day": "Thursday",
    "daypart": "morning",
    "hour": "9h - 12h",
    "organisation": "CPF Marolles",
    "address": "Rue de la Roue 21, 1000 Brusselss",
    "telephone": "02 426 06 27",
    "email": "",
    "website": "",
    "startTime": "2021-07-29T07:00:10.366Z",
    "endTime": "2021-07-29T10:00:10.366Z"
  },
  {
    "place": "Brussels",
    "appointment": "no",
    "free": "yes",
    "day": "Friday",
    "daypart": "morning",
    "hour": "9h - 12h",
    "organisation": "CPF Marolles",
    "address": "Rue de la Roue 21, 1000 Brusselss",
    "telephone": "02 426 06 27",
    "email": "",
    "website": "",
    "startTime": "2021-07-30T07:00:10.366Z",
    "endTime": "2021-07-30T10:00:10.366Z"
  },
  {
    "place": "Brussels",
    "appointment": "no",
    "free": "yes",
    "day": "Monday",
    "daypart": "afternoon",
    "hour": "12h30 - 17h30",
    "organisation": "CPF Marolles",
    "address": "Rue de la Roue 21, 1000 Brusselss",
    "telephone": "02 426 06 27",
    "email": "",
    "website": "",
    "startTime": "2021-07-26T10:30:10.366Z",
    "endTime": "2021-07-26T15:30:10.366Z"
  },
  {
    "place": "Brussels",
    "appointment": "no",
    "free": "yes",
    "day": "Tuesday",
    "daypart": "afternoon",
    "hour": "12h30 - 17h30",
    "organisation": "CPF Marolles",
    "address": "Rue de la Roue 21, 1000 Brusselss",
    "telephone": "02 426 06 27",
    "email": "",
    "website": "",
    "startTime": "2021-07-27T10:30:10.366Z",
    "endTime": "2021-07-27T15:30:10.366Z"
  },
  {
    "place": "Brussels",
    "appointment": "no",
    "free": "yes",
    "day": "Wednesday",
    "daypart": "afternoon",
    "hour": "12h30 - 17h30",
    "organisation": "CPF Marolles",
    "address": "Rue de la Roue 21, 1000 Brusselss",
    "telephone": "02 426 06 27",
    "email": "",
    "website": "",
    "startTime": "2021-07-28T10:30:10.366Z",
    "endTime": "2021-07-28T15:30:10.366Z"
  },
  {
    "place": "Brussels",
    "appointment": "no",
    "free": "yes",
    "day": "Thursday",
    "daypart": "afternoon",
    "hour": "12h30 - 18h30",
    "organisation": "CPF Marolles",
    "address": "Rue de la Roue 21, 1000 Brusselss",
    "telephone": "02 426 06 27",
    "email": "",
    "website": "",
    "startTime": "2021-07-29T10:30:10.366Z",
    "endTime": "2021-07-29T16:30:10.366Z"
  },
  {
    "place": "Brussels",
    "appointment": "no",
    "free": "yes",
    "day": "Friday",
    "daypart": "afternoon",
    "hour": "12h30 - 17h30",
    "organisation": "CPF Marolles",
    "address": "Rue de la Roue 21, 1000 Brusselss",
    "telephone": "02 426 06 27",
    "email": "",
    "website": "",
    "startTime": "2021-07-30T10:30:10.366Z",
    "endTime": "2021-07-30T15:30:10.366Z"
  },
  {
    "place": "Brussels",
    "appointment": "no",
    "free": "yes",
    "day": "Thursday",
    "daypart": "afternoon",
    "hour": "18/7: 17h - 19h",
    "organisation": "CPF Watermael-Boitsfort",
    "address": "Avenue Léopold Wiener 64, 1170 Brussels",
    "telephone": "02 673 39 34",
    "email": "",
    "website": "",
    "startTime": "2021-07-29T12:00:10.367Z",
    "endTime": "2021-07-29T17:00:10.367Z"
  },
  {
    "place": "Brussels",
    "appointment": "no",
    "free": "yes",
    "day": "Thursday",
    "daypart": "afternoon",
    "hour": "19/9: 17h - 19h",
    "organisation": "CPF Watermael-Boitsfort",
    "address": "Avenue Léopold Wiener 64, 1170 Brussels",
    "telephone": "02 673 39 34",
    "email": "",
    "website": "",
    "startTime": "2021-07-29T12:00:10.367Z",
    "endTime": "2021-07-29T17:00:10.367Z"
  },
  {
    "place": "Brussels",
    "appointment": "no",
    "free": "yes",
    "day": "Thursday",
    "daypart": "afternoon",
    "hour": "18/7: 17h - 19h",
    "organisation": "CPF Watermael-Boitsfort",
    "address": "Avenue Léopold Wiener 64, 1170 Brussels",
    "telephone": "02 673 39 34",
    "email": "",
    "website": "",
    "startTime": "2021-07-29T12:00:10.367Z",
    "endTime": "2021-07-29T17:00:10.367Z"
  },
  {
    "place": "Brussels",
    "appointment": "no",
    "free": "yes",
    "day": "Thursday",
    "daypart": "afternoon",
    "hour": "17/10: 17h - 19h",
    "organisation": "CPF Watermael-Boitsfort",
    "address": "Avenue Léopold Wiener 64, 1170 Brussels",
    "telephone": "02 673 39 34",
    "email": "",
    "website": "",
    "startTime": "2021-07-29T12:00:10.367Z",
    "endTime": "2021-07-29T17:00:10.367Z"
  },
  {
    "place": "Brussels",
    "appointment": "no",
    "free": "yes",
    "day": "Thursday",
    "daypart": "afternoon",
    "hour": "21/11: 17h - 19h",
    "organisation": "CPF Watermael-Boitsfort",
    "address": "Avenue Léopold Wiener 64, 1170 Brussels",
    "telephone": "02 673 39 34",
    "email": "",
    "website": "",
    "startTime": "2021-07-29T12:00:10.367Z",
    "endTime": "2021-07-29T17:00:10.367Z"
  },
  {
    "place": "Brussels",
    "appointment": "no",
    "free": "yes",
    "day": "Thursday",
    "daypart": "afternoon",
    "hour": "19/12: 17h - 19h",
    "organisation": "CPF Watermael-Boitsfort",
    "address": "Avenue Léopold Wiener 64, 1170 Brussels",
    "telephone": "02 673 39 34",
    "email": "",
    "website": "",
    "startTime": "2021-07-29T12:00:10.367Z",
    "endTime": "2021-07-29T17:00:10.367Z"
  },
  {
    "place": "Brussels",
    "appointment": "no",
    "free": "yes",
    "day": "Tuesday",
    "daypart": "afternoon",
    "hour": "9/7: 16h - 18h",
    "organisation": "CPF Uccle",
    "address": "Rue de Stalle 24, 1180 Brussels",
    "telephone": "02 376 10 00",
    "email": "",
    "website": "",
    "startTime": "2021-07-27T12:00:10.368Z",
    "endTime": "2021-07-27T16:00:10.368Z"
  },
  {
    "place": "Brussels",
    "appointment": "no",
    "free": "yes",
    "day": "Tuesday",
    "daypart": "afternoon",
    "hour": "13/8: 16h - 18h",
    "organisation": "CPF Uccle",
    "address": "Rue de Stalle 24, 1180 Brussels",
    "telephone": "02 376 10 00",
    "email": "",
    "website": "",
    "startTime": "2021-07-27T12:00:10.368Z",
    "endTime": "2021-07-27T16:00:10.368Z"
  },
  {
    "place": "Brussels",
    "appointment": "no",
    "free": "yes",
    "day": "Tuesday",
    "daypart": "afternoon",
    "hour": "10/9: 16h - 18h",
    "organisation": "CPF Uccle",
    "address": "Rue de Stalle 24, 1180 Brussels",
    "telephone": "02 376 10 00",
    "email": "",
    "website": "",
    "startTime": "2021-07-27T12:00:10.368Z",
    "endTime": "2021-07-27T16:00:10.368Z"
  },
  {
    "place": "Brussels",
    "appointment": "no",
    "free": "yes",
    "day": "Tuesday",
    "daypart": "afternoon",
    "hour": "8/10: 16h - 18h",
    "organisation": "CPF Uccle",
    "address": "Rue de Stalle 24, 1180 Brussels",
    "telephone": "02 376 10 00",
    "email": "",
    "website": "",
    "startTime": "2021-07-27T12:00:10.368Z",
    "endTime": "2021-07-27T16:00:10.368Z"
  },
  {
    "place": "Brussels",
    "appointment": "no",
    "free": "yes",
    "day": "Tuesday",
    "daypart": "afternoon",
    "hour": "12/11: 16h - 18h",
    "organisation": "CPF Uccle",
    "address": "Rue de Stalle 24, 1180 Brussels",
    "telephone": "02 376 10 00",
    "email": "",
    "website": "",
    "startTime": "2021-07-27T12:00:10.368Z",
    "endTime": "2021-07-27T16:00:10.368Z"
  },
  {
    "place": "Brussels",
    "appointment": "no",
    "free": "yes",
    "day": "Tuesday",
    "daypart": "afternoon",
    "hour": "10/12: 16h - 18h",
    "organisation": "CPF Uccle",
    "address": "Rue de Stalle 24, 1180 Brussels",
    "telephone": "02 376 10 00",
    "email": "",
    "website": "",
    "startTime": "2021-07-27T12:00:10.368Z",
    "endTime": "2021-07-27T16:00:10.368Z"
  },
  {
    "place": "Antwerp",
    "appointment": "yes",
    "free": "no",
    "day": "Tuesday",
    "daypart": "morning",
    "hour": "9h - 12h",
    "organisation": "Help Centre",
    "address": "Kronenburgstraat 43, 2000 Antwerp",
    "telephone": "03 216 02 88",
    "email": "helpcenter@itg.be",
    "website": "https://www.itg.be/E/helpcenter",
    "startTime": "2021-07-27T07:00:10.369Z",
    "endTime": "2021-07-27T10:00:10.369Z"
  },
  {
    "place": "Antwerp",
    "appointment": "yes",
    "free": "no",
    "day": "Wednesday",
    "daypart": "morning",
    "hour": "9h - 12h",
    "organisation": "Help Centre",
    "address": "Kronenburgstraat 43, 2000 Antwerp",
    "telephone": "03 216 02 88",
    "email": "helpcenter@itg.be",
    "website": "https://www.itg.be/E/helpcenter",
    "startTime": "2021-07-28T07:00:10.369Z",
    "endTime": "2021-07-28T10:00:10.369Z"
  },
  {
    "place": "Antwerp",
    "appointment": "no",
    "free": "no",
    "day": "Monday",
    "daypart": "afternoon",
    "hour": "14h - 16h",
    "organisation": "Help Centre",
    "address": "Kronenburgstraat 43, 2000 Antwerp",
    "telephone": "03 216 02 88",
    "email": "helpcenter@itg.be",
    "website": "https://www.itg.be/E/helpcenter",
    "startTime": "2021-07-26T12:00:10.369Z",
    "endTime": "2021-07-26T14:00:10.369Z"
  },
  {
    "place": "Antwerp",
    "appointment": "no",
    "free": "no",
    "day": "Thursday",
    "daypart": "afternoon",
    "hour": "14h - 16h",
    "organisation": "Help Centre",
    "address": "Kronenburgstraat 43, 2000 Antwerp",
    "telephone": "03 216 02 88",
    "email": "helpcenter@itg.be",
    "website": "https://www.itg.be/E/helpcenter",
    "startTime": "2021-07-29T12:00:10.369Z",
    "endTime": "2021-07-29T14:00:10.369Z"
  },
  {
    "place": "Antwerp",
    "appointment": "no",
    "free": "no",
    "day": "Friday",
    "daypart": "afternoon",
    "hour": "14h - 16h",
    "organisation": "Help Centre",
    "address": "Kronenburgstraat 43, 2000 Antwerp",
    "telephone": "03 216 02 88",
    "email": "helpcenter@itg.be",
    "website": "https://www.itg.be/E/helpcenter",
    "startTime": "2021-07-30T12:00:10.369Z",
    "endTime": "2021-07-30T14:00:10.369Z"
  },
  {
    "place": "SexBru",
    "appointment": "no",
    "free": "yes",
    "day": "Tuesday",
    "daypart": "afternoon",
    "hour": "19h - 21h",
    "organisation": "Alias",
    "address": "Rue du Marché au charbon 33, Brussels",
    "telephone": "0485 547 278 (Aure)",
    "email": "aure@alias-bru.be",
    "website": "http://www.alias-bru.be/permanence-medicale/",
    "startTime": "2021-07-27T17:00:10.371Z",
    "endTime": "2021-07-27T19:00:10.371Z"
  },
  {
    "place": "SexAnt",
    "appointment": "no",
    "free": "yes",
    "day": "Wednesday",
    "daypart": "afternoon",
    "hour": "3/7: 14h30 - 16h30",
    "organisation": "Boysproject",
    "address": "Appelmansstraat 12, 2018 Antwerp",
    "telephone": "03 293 95 90",
    "email": "info@boysproject.be",
    "website": "http://www.boysproject.be/en/offer/TESTING",
    "startTime": "2021-07-28T12:30:10.371Z",
    "endTime": "2021-07-28T14:30:10.371Z"
  },
  {
    "place": "SexAnt",
    "appointment": "no",
    "free": "yes",
    "day": "Wednesday",
    "daypart": "afternoon",
    "hour": "17/7: 18h - 20h",
    "organisation": "Boysproject",
    "address": "Appelmansstraat 12, 2018 Antwerp",
    "telephone": "03 293 95 90",
    "email": "info@boysproject.be",
    "website": "http://www.boysproject.be/en/offer/TESTING",
    "startTime": "2021-07-28T12:00:10.371Z",
    "endTime": "2021-07-28T18:00:10.371Z"
  },
  {
    "place": "SexAnt",
    "appointment": "no",
    "free": "yes",
    "day": "Wednesday",
    "daypart": "afternoon",
    "hour": "31/7: 14h30 - 16h30",
    "organisation": "Boysproject",
    "address": "Appelmansstraat 12, 2018 Antwerp",
    "telephone": "03 293 95 90",
    "email": "info@boysproject.be",
    "website": "http://www.boysproject.be/en/offer/TESTING",
    "startTime": "2021-07-28T12:30:10.371Z",
    "endTime": "2021-07-28T14:30:10.371Z"
  },
  {
    "place": "SexAnt",
    "appointment": "no",
    "free": "yes",
    "day": "Wednesday",
    "daypart": "afternoon",
    "hour": "14/8: 18h - 20h",
    "organisation": "Boysproject",
    "address": "Appelmansstraat 12, 2018 Antwerp",
    "telephone": "03 293 95 90",
    "email": "info@boysproject.be",
    "website": "http://www.boysproject.be/en/offer/TESTING",
    "startTime": "2021-07-28T12:00:10.371Z",
    "endTime": "2021-07-28T18:00:10.371Z"
  },
  {
    "place": "SexAnt",
    "appointment": "no",
    "free": "yes",
    "day": "Wednesday",
    "daypart": "afternoon",
    "hour": "28/8: 14h30 - 16h30",
    "organisation": "Boysproject",
    "address": "Appelmansstraat 12, 2018 Antwerp",
    "telephone": "03 293 95 90",
    "email": "info@boysproject.be",
    "website": "http://www.boysproject.be/en/offer/TESTING",
    "startTime": "2021-07-28T12:30:10.371Z",
    "endTime": "2021-07-28T14:30:10.372Z"
  },
  {
    "place": "SexAnt",
    "appointment": "no",
    "free": "yes",
    "day": "Wednesday",
    "daypart": "afternoon",
    "hour": "11/9: 18h - 20h",
    "organisation": "Boysproject",
    "address": "Appelmansstraat 12, 2018 Antwerp",
    "telephone": "03 293 95 90",
    "email": "info@boysproject.be",
    "website": "http://www.boysproject.be/en/offer/TESTING",
    "startTime": "2021-07-28T12:00:10.372Z",
    "endTime": "2021-07-28T18:00:10.372Z"
  },
  {
    "place": "SexAnt",
    "appointment": "no",
    "free": "yes",
    "day": "Wednesday",
    "daypart": "afternoon",
    "hour": "25/9: 14h30 - 16h30",
    "organisation": "Boysproject",
    "address": "Appelmansstraat 12, 2018 Antwerp",
    "telephone": "03 293 95 90",
    "email": "info@boysproject.be",
    "website": "http://www.boysproject.be/en/offer/TESTING",
    "startTime": "2021-07-28T12:30:10.372Z",
    "endTime": "2021-07-28T14:30:10.372Z"
  },
  {
    "place": "SexAnt",
    "appointment": "no",
    "free": "yes",
    "day": "Wednesday",
    "daypart": "afternoon",
    "hour": "9/10: 18h - 20h",
    "organisation": "Boysproject",
    "address": "Appelmansstraat 12, 2018 Antwerp",
    "telephone": "03 293 95 90",
    "email": "info@boysproject.be",
    "website": "http://www.boysproject.be/en/offer/TESTING",
    "startTime": "2021-07-28T12:00:10.372Z",
    "endTime": "2021-07-28T18:00:10.372Z"
  },
  {
    "place": "SexAnt",
    "appointment": "no",
    "free": "yes",
    "day": "Wednesday",
    "daypart": "afternoon",
    "hour": "23/10: 14h30 - 16h30",
    "organisation": "Boysproject",
    "address": "Appelmansstraat 12, 2018 Antwerp",
    "telephone": "03 293 95 90",
    "email": "info@boysproject.be",
    "website": "http://www.boysproject.be/en/offer/TESTING",
    "startTime": "2021-07-28T12:30:10.372Z",
    "endTime": "2021-07-28T14:30:10.372Z"
  },
  {
    "place": "SexOther",
    "appointment": "no",
    "free": "yes",
    "day": "Monday",
    "daypart": "afternoon",
    "hour": "14h - 16h",
    "organisation": "Violett",
    "address": "Verversrui 3, 2000 Antwerp",
    "telephone": "03 293 95 91",
    "email": "dokters.Antwerpen@violett.be",
    "website": "https://www.violett.be/nl/laat-je-testen/",
    "startTime": "2021-07-26T12:00:10.372Z",
    "endTime": "2021-07-26T14:00:10.372Z"
  },
  {
    "place": "SexOther",
    "appointment": "no",
    "free": "yes",
    "day": "Wednesday",
    "daypart": "morning",
    "hour": "10h - 12h",
    "organisation": "Violett",
    "address": "Verversrui 3, 2000 Antwerp",
    "telephone": "03 293 95 91",
    "email": "dokters.Antwerpen@violett.be",
    "website": "https://www.violett.be/nl/laat-je-testen/",
    "startTime": "2021-07-28T08:00:10.372Z",
    "endTime": "2021-07-28T10:00:10.372Z"
  },
  {
    "place": "SexOther",
    "appointment": "no",
    "free": "yes",
    "day": "Wednesday",
    "daypart": "afternoon",
    "hour": "18h - 20h",
    "organisation": "Violett",
    "address": "Verversrui 3, 2000 Antwerp",
    "telephone": "03 293 95 91",
    "email": "dokters.Antwerpen@violett.be",
    "website": "https://www.violett.be/nl/laat-je-testen/",
    "startTime": "2021-07-28T16:00:10.372Z",
    "endTime": "2021-07-28T18:00:10.373Z"
  },
  {
    "place": "SexOther",
    "appointment": "no",
    "free": "yes",
    "day": "Friday",
    "daypart": "morning",
    "hour": "10h - 12h",
    "organisation": "Violett",
    "address": "Verversrui 3, 2000 Antwerp",
    "telephone": "03 293 95 91",
    "email": "dokters.Antwerpen@violett.be",
    "website": "https://www.violett.be/nl/laat-je-testen/",
    "startTime": "2021-07-30T08:00:10.373Z",
    "endTime": "2021-07-30T10:00:10.373Z"
  },
  {
    "place": "SexOther",
    "appointment": "yes",
    "free": "yes",
    "day": "Wednesday",
    "daypart": "afternoon",
    "hour": "18h30 - 19h30",
    "organisation": "Violett",
    "address": "Verversrui 3, 2000 Antwerp",
    "telephone": "03 293 95 91",
    "email": "dokters.Antwerpen@violett.be",
    "website": "https://www.violett.be/nl/laat-je-testen/",
    "startTime": "2021-07-28T16:30:10.373Z",
    "endTime": "2021-07-28T17:30:10.373Z"
  },
  {
    "place": "SexOther",
    "appointment": "no",
    "free": "yes",
    "day": "Friday",
    "daypart": "morning",
    "hour": "11h - 12h",
    "organisation": "Violett",
    "address": "Brabantdam 100B, 9000 Ghent",
    "telephone": "09 233 47 67",
    "email": "dokters.gent@violett.be",
    "website": "https://www.violett.be/nl/laat-je-testen/",
    "startTime": "2021-07-30T09:00:10.373Z",
    "endTime": "2021-07-30T10:00:10.373Z"
  },
  {
    "place": "SexOther",
    "appointment": "no",
    "free": "yes",
    "day": "Friday",
    "daypart": "afternoon",
    "hour": "12h - 13h",
    "organisation": "Violett",
    "address": "Brabantdam 100B, 9000 Ghent",
    "telephone": "09 233 47 67",
    "email": "dokters.gent@violett.be",
    "website": "https://www.violett.be/nl/laat-je-testen/",
    "startTime": "2021-07-30T10:00:10.373Z",
    "endTime": "2021-07-30T11:00:10.374Z"
  },
  {
    "place": "SexOther",
    "appointment": "no",
    "free": "yes",
    "day": "Monday",
    "daypart": "morning",
    "hour": "10h - 12h",
    "organisation": "Violett",
    "address": "Ertbeekstraat 34, 3500 Hasselt",
    "telephone": "011 33 30 58",
    "email": "dokters.hasselt@violett.be",
    "website": "https://www.violett.be/nl/laat-je-testen/",
    "startTime": "2021-07-26T08:00:10.374Z",
    "endTime": "2021-07-26T10:00:10.374Z"
  },
  {
    "place": "Brussels",
    "appointment": "no",
    "free": "yes",
    "day": "Monday",
    "daypart": "afternoon",
    "hour": "8/7: 18h - 21h",
    "organisation": "Aide Info Sida",
    "address": "Rue Duquesnoy 45, 1000 Brussels",
    "telephone": "02 514 29 65",
    "email": "aide.info.sida@gmail.com",
    "website": "http://www.aideinfosida.be/tests_ais.php",
    "startTime": "2021-07-26T12:00:10.374Z",
    "endTime": "2021-07-26T19:00:10.374Z"
  },
  {
    "place": "Brussels",
    "appointment": "no",
    "free": "yes",
    "day": "Monday",
    "daypart": "afternoon",
    "hour": "12/8: 18h - 21h",
    "organisation": "Aide Info Sida",
    "address": "Rue Duquesnoy 45, 1000 Brussels",
    "telephone": "02 514 29 65",
    "email": "aide.info.sida@gmail.com",
    "website": "http://www.aideinfosida.be/tests_ais.php",
    "startTime": "2021-07-26T12:00:10.374Z",
    "endTime": "2021-07-26T19:00:10.374Z"
  },
  {
    "place": "Brussels",
    "appointment": "no",
    "free": "yes",
    "day": "Monday",
    "daypart": "afternoon",
    "hour": "26/8: 18h - 21h",
    "organisation": "Aide Info Sida",
    "address": "Rue Duquesnoy 45, 1000 Brussels",
    "telephone": "02 514 29 65",
    "email": "aide.info.sida@gmail.com",
    "website": "http://www.aideinfosida.be/tests_ais.php",
    "startTime": "2021-07-26T12:00:10.375Z",
    "endTime": "2021-07-26T19:00:10.375Z"
  },
  {
    "place": "Brussels",
    "appointment": "no",
    "free": "yes",
    "day": "Tuesday",
    "daypart": "afternoon",
    "hour": "9/9: 18h - 21h",
    "organisation": "Aide Info Sida",
    "address": "Rue Duquesnoy 45, 1000 Brussels",
    "telephone": "02 514 29 65",
    "email": "aide.info.sida@gmail.com",
    "website": "http://www.aideinfosida.be/tests_ais.php",
    "startTime": "2021-07-27T12:00:10.375Z",
    "endTime": "2021-07-27T19:00:10.375Z"
  },
  {
    "place": "Brussels",
    "appointment": "no",
    "free": "yes",
    "day": "Wednesday",
    "daypart": "afternoon",
    "hour": "23/9: 18h - 21h",
    "organisation": "Aide Info Sida",
    "address": "Rue Duquesnoy 45, 1000 Brussels",
    "telephone": "02 514 29 65",
    "email": "aide.info.sida@gmail.com",
    "website": "http://www.aideinfosida.be/tests_ais.php",
    "startTime": "2021-07-28T12:00:10.375Z",
    "endTime": "2021-07-28T19:00:10.375Z"
  },
  {
    "place": "Brussels",
    "appointment": "no",
    "free": "yes",
    "day": "Thursday",
    "daypart": "afternoon",
    "hour": "26/8: 18h - 21h",
    "organisation": "Aide Info Sida",
    "address": "Rue Duquesnoy 45, 1000 Brussels",
    "telephone": "02 514 29 65",
    "email": "aide.info.sida@gmail.com",
    "website": "http://www.aideinfosida.be/tests_ais.php",
    "startTime": "2021-07-29T12:00:10.376Z",
    "endTime": "2021-07-29T19:00:10.376Z"
  },
  {
    "place": "Brussels",
    "appointment": "no",
    "free": "yes",
    "day": "Friday",
    "daypart": "afternoon",
    "hour": "14/10: 18h - 21h",
    "organisation": "Aide Info Sida",
    "address": "Rue Duquesnoy 45, 1000 Brussels",
    "telephone": "02 514 29 65",
    "email": "aide.info.sida@gmail.com",
    "website": "http://www.aideinfosida.be/tests_ais.php",
    "startTime": "2021-07-30T12:00:10.376Z",
    "endTime": "2021-07-30T19:00:10.376Z"
  },
  {
    "place": "Brussels",
    "appointment": "no",
    "free": "yes",
    "day": "Saturday",
    "daypart": "afternoon",
    "hour": "28/10: 18h - 21h",
    "organisation": "Aide Info Sida",
    "address": "Rue Duquesnoy 45, 1000 Brussels",
    "telephone": "02 514 29 65",
    "email": "aide.info.sida@gmail.com",
    "website": "http://www.aideinfosida.be/tests_ais.php",
    "startTime": "2021-07-31T12:00:10.376Z",
    "endTime": "2021-07-31T19:00:10.376Z"
  },
  {
    "place": "Brussels",
    "appointment": "no",
    "free": "yes",
    "day": "Sunday",
    "daypart": "afternoon",
    "hour": "25/11: 18h - 21h",
    "organisation": "Aide Info Sida",
    "address": "Rue Duquesnoy 45, 1000 Brussels",
    "telephone": "02 514 29 65",
    "email": "aide.info.sida@gmail.com",
    "website": "http://www.aideinfosida.be/tests_ais.php",
    "startTime": "2021-07-25T12:00:10.376Z",
    "endTime": "2021-07-25T19:00:10.376Z"
  },
  {
    "place": "Brussels",
    "appointment": "no",
    "free": "yes",
    "day": "Monday",
    "daypart": "afternoon",
    "hour": "9/12: 18h - 21h",
    "organisation": "Aide Info Sida",
    "address": "Rue Duquesnoy 45, 1000 Brussels",
    "telephone": "02 514 29 65",
    "email": "aide.info.sida@gmail.com",
    "website": "http://www.aideinfosida.be/tests_ais.php",
    "startTime": "2021-07-26T12:00:10.376Z",
    "endTime": "2021-07-26T19:00:10.376Z"
  },
  {
    "place": "Brussels",
    "appointment": "no",
    "free": "yes",
    "day": "Tuesday",
    "daypart": "afternoon",
    "hour": "23/12: 18h - 21h",
    "organisation": "Aide Info Sida",
    "address": "Rue Duquesnoy 45, 1000 Brussels",
    "telephone": "02 514 29 65",
    "email": "aide.info.sida@gmail.com",
    "website": "http://www.aideinfosida.be/tests_ais.php",
    "startTime": "2021-07-27T12:00:10.377Z",
    "endTime": "2021-07-27T19:00:10.377Z"
  },
  {
    "place": "Brussels",
    "appointment": "no",
    "free": "no",
    "day": "Wednesday",
    "daypart": "morning",
    "hour": "10/7: 9h - 12h",
    "organisation": "CPF Senne",
    "address": "Boulevard de l'Abattoir 27, Brussels",
    "telephone": "02 548 98 18",
    "email": "planning@tele-service.be",
    "website": "https://www.cpfsenne.be/spip.php?rubrique13",
    "startTime": "2021-07-28T12:00:10.377Z",
    "endTime": "2021-07-28T10:00:10.377Z"
  },
  {
    "place": "Brussels",
    "appointment": "yes",
    "free": "no",
    "day": "Wednesday",
    "daypart": "morning",
    "hour": "10/7: 9h - 12h",
    "organisation": "CPF Senne",
    "address": "Boulevard de l'Abattoir 27, Brussels",
    "telephone": "02 548 98 18",
    "email": "planning@tele-service.be",
    "website": "https://www.cpfsenne.be/spip.php?rubrique14",
    "startTime": "2021-07-28T12:00:10.377Z",
    "endTime": "2021-07-28T10:00:10.377Z"
  },
  {
    "place": "Brussels",
    "appointment": "no",
    "free": "no",
    "day": "Wednesday",
    "daypart": "morning",
    "hour": "17/7: 9h - 12h",
    "organisation": "CPF Senne",
    "address": "Boulevard de l'Abattoir 27, Brussels",
    "telephone": "02 548 98 18",
    "email": "planning@tele-service.be",
    "website": "https://www.cpfsenne.be/spip.php?rubrique15",
    "startTime": "2021-07-28T12:00:10.377Z",
    "endTime": "2021-07-28T10:00:10.377Z"
  },
  {
    "place": "Brussels",
    "appointment": "yes",
    "free": "no",
    "day": "Wednesday",
    "daypart": "morning",
    "hour": "17/7: 9h - 12h",
    "organisation": "CPF Senne",
    "address": "Boulevard de l'Abattoir 27, Brussels",
    "telephone": "02 548 98 18",
    "email": "planning@tele-service.be",
    "website": "https://www.cpfsenne.be/spip.php?rubrique16",
    "startTime": "2021-07-28T12:00:10.377Z",
    "endTime": "2021-07-28T10:00:10.377Z"
  },
  {
    "place": "Brussels",
    "appointment": "no",
    "free": "no",
    "day": "Wednesday",
    "daypart": "morning",
    "hour": "24/7: 9h - 12h",
    "organisation": "CPF Senne",
    "address": "Boulevard de l'Abattoir 27, Brussels",
    "telephone": "02 548 98 18",
    "email": "planning@tele-service.be",
    "website": "https://www.cpfsenne.be/spip.php?rubrique17",
    "startTime": "2021-07-28T12:00:10.377Z",
    "endTime": "2021-07-28T10:00:10.377Z"
  },
  {
    "place": "Brussels",
    "appointment": "yes",
    "free": "no",
    "day": "Wednesday",
    "daypart": "morning",
    "hour": "24/7: 9h - 12h",
    "organisation": "CPF Senne",
    "address": "Boulevard de l'Abattoir 27, Brussels",
    "telephone": "02 548 98 18",
    "email": "planning@tele-service.be",
    "website": "https://www.cpfsenne.be/spip.php?rubrique18",
    "startTime": "2021-07-28T12:00:10.377Z",
    "endTime": "2021-07-28T10:00:10.378Z"
  },
  {
    "place": "Brussels",
    "appointment": "no",
    "free": "no",
    "day": "Wednesday",
    "daypart": "morning",
    "hour": "31/7: 9h - 12h",
    "organisation": "CPF Senne",
    "address": "Boulevard de l'Abattoir 27, Brussels",
    "telephone": "02 548 98 18",
    "email": "planning@tele-service.be",
    "website": "https://www.cpfsenne.be/spip.php?rubrique19",
    "startTime": "2021-07-28T12:00:10.378Z",
    "endTime": "2021-07-28T10:00:10.378Z"
  },
  {
    "place": "Brussels",
    "appointment": "yes",
    "free": "no",
    "day": "Wednesday",
    "daypart": "morning",
    "hour": "31/7: 9h - 12h",
    "organisation": "CPF Senne",
    "address": "Boulevard de l'Abattoir 27, Brussels",
    "telephone": "02 548 98 18",
    "email": "planning@tele-service.be",
    "website": "https://www.cpfsenne.be/spip.php?rubrique20",
    "startTime": "2021-07-28T12:00:10.378Z",
    "endTime": "2021-07-28T10:00:10.378Z"
  },
  {
    "place": "Brussels",
    "appointment": "no",
    "free": "no",
    "day": "Wednesday",
    "daypart": "morning",
    "hour": "7/8: 9h - 12h",
    "organisation": "CPF Senne",
    "address": "Boulevard de l'Abattoir 27, Brussels",
    "telephone": "02 548 98 18",
    "email": "planning@tele-service.be",
    "website": "https://www.cpfsenne.be/spip.php?rubrique21",
    "startTime": "2021-07-28T12:00:10.378Z",
    "endTime": "2021-07-28T10:00:10.378Z"
  },
  {
    "place": "Brussels",
    "appointment": "yes",
    "free": "no",
    "day": "Wednesday",
    "daypart": "morning",
    "hour": "7/8: 9h - 12h",
    "organisation": "CPF Senne",
    "address": "Boulevard de l'Abattoir 27, Brussels",
    "telephone": "02 548 98 18",
    "email": "planning@tele-service.be",
    "website": "https://www.cpfsenne.be/spip.php?rubrique22",
    "startTime": "2021-07-28T12:00:10.378Z",
    "endTime": "2021-07-28T10:00:10.378Z"
  },
  {
    "place": "Brussels",
    "appointment": "yes",
    "free": "no",
    "day": "Wednesday",
    "daypart": "morning",
    "hour": "29/8: 9h - 12h",
    "organisation": "CPF Senne",
    "address": "Boulevard de l'Abattoir 27, Brussels",
    "telephone": "02 548 98 18",
    "email": "planning@tele-service.be",
    "website": "https://www.cpfsenne.be/spip.php?rubrique23",
    "startTime": "2021-07-28T12:00:10.378Z",
    "endTime": "2021-07-28T10:00:10.378Z"
  },
  {
    "place": "Brussels",
    "appointment": "no",
    "free": "no",
    "day": "Wednesday",
    "daypart": "morning",
    "hour": "29/8: 9h - 12h",
    "organisation": "CPF Senne",
    "address": "Boulevard de l'Abattoir 27, Brussels",
    "telephone": "02 548 98 18",
    "email": "planning@tele-service.be",
    "website": "https://www.cpfsenne.be/spip.php?rubrique24",
    "startTime": "2021-07-28T12:00:10.378Z",
    "endTime": "2021-07-28T10:00:10.378Z"
  },
  {
    "place": "Brussels",
    "appointment": "yes",
    "free": "no",
    "day": "Monday",
    "daypart": "morning",
    "hour": "9h - 12h",
    "organisation": "CPF Plan F",
    "address": "Rue des Guildes 22, 1000 Brussels",
    "telephone": "02 230 04 62",
    "email": "",
    "website": "http://www.planf.be/Horaires",
    "startTime": "2021-07-26T07:00:10.378Z",
    "endTime": "2021-07-26T10:00:10.379Z"
  },
  {
    "place": "Brussels",
    "appointment": "yes",
    "free": "no",
    "day": "Monday",
    "daypart": "afternoon",
    "hour": "14h - 18h",
    "organisation": "CPF Plan F",
    "address": "Rue des Guildes 22, 1000 Brussels",
    "telephone": "02 230 04 62",
    "email": "",
    "website": "http://www.planf.be/Horaires",
    "startTime": "2021-07-26T12:00:10.379Z",
    "endTime": "2021-07-26T16:00:10.379Z"
  },
  {
    "place": "Brussels",
    "appointment": "yes",
    "free": "no",
    "day": "Tuesday",
    "daypart": "morning",
    "hour": "9h - 13h30",
    "organisation": "CPF Plan F",
    "address": "Rue des Guildes 22, 1000 Brussels",
    "telephone": "02 230 04 62",
    "email": "",
    "website": "http://www.planf.be/Horaires",
    "startTime": "2021-07-27T07:00:10.379Z",
    "endTime": "2021-07-27T11:30:10.379Z"
  },
  {
    "place": "Brussels",
    "appointment": "yes",
    "free": "no",
    "day": "Tuesday",
    "daypart": "afternoon",
    "hour": "14h - 18h",
    "organisation": "CPF Plan F",
    "address": "Rue des Guildes 22, 1000 Brussels",
    "telephone": "02 230 04 62",
    "email": "",
    "website": "http://www.planf.be/Horaires",
    "startTime": "2021-07-27T12:00:10.379Z",
    "endTime": "2021-07-27T16:00:10.379Z"
  },
  {
    "place": "Brussels",
    "appointment": "yes",
    "free": "no",
    "day": "Wednesday",
    "daypart": "morning",
    "hour": "9h30 - 13h",
    "organisation": "CPF Plan F",
    "address": "Rue des Guildes 22, 1000 Brussels",
    "telephone": "02 230 04 62",
    "email": "",
    "website": "http://www.planf.be/Horaires",
    "startTime": "2021-07-28T07:30:10.379Z",
    "endTime": "2021-07-28T11:00:10.379Z"
  },
  {
    "place": "Brussels",
    "appointment": "yes",
    "free": "no",
    "day": "Wednesday",
    "daypart": "afternoon",
    "hour": "14h - 17h",
    "organisation": "CPF Plan F",
    "address": "Rue des Guildes 22, 1000 Brussels",
    "telephone": "02 230 04 62",
    "email": "",
    "website": "http://www.planf.be/Horaires",
    "startTime": "2021-07-28T12:00:10.379Z",
    "endTime": "2021-07-28T15:00:10.379Z"
  },
  {
    "place": "Brussels",
    "appointment": "yes",
    "free": "no",
    "day": "Thursday",
    "daypart": "morning",
    "hour": "9h - 13h",
    "organisation": "CPF Plan F",
    "address": "Rue des Guildes 22, 1000 Brussels",
    "telephone": "02 230 04 62",
    "email": "",
    "website": "http://www.planf.be/Horaires",
    "startTime": "2021-07-29T07:00:10.379Z",
    "endTime": "2021-07-29T11:00:10.379Z"
  },
  {
    "place": "Brussels",
    "appointment": "yes",
    "free": "no",
    "day": "Thursday",
    "daypart": "afternoon",
    "hour": "14h30 - 18h30",
    "organisation": "CPF Plan F",
    "address": "Rue des Guildes 22, 1000 Brussels",
    "telephone": "02 230 04 62",
    "email": "",
    "website": "http://www.planf.be/Horaires",
    "startTime": "2021-07-29T12:30:10.379Z",
    "endTime": "2021-07-29T16:30:10.379Z"
  },
  {
    "place": "Brussels",
    "appointment": "yes",
    "free": "no",
    "day": "Friday",
    "daypart": "morning",
    "hour": "9h30 - 13h30",
    "organisation": "CPF Plan F",
    "address": "Rue des Guildes 22, 1000 Brussels",
    "telephone": "02 230 04 62",
    "email": "",
    "website": "http://www.planf.be/Horaires",
    "startTime": "2021-07-30T07:30:10.380Z",
    "endTime": "2021-07-30T11:30:10.380Z"
  },
  {
    "place": "Brussels",
    "appointment": "yes",
    "free": "no",
    "day": "Friday",
    "daypart": "afternoon",
    "hour": "14h - 18h",
    "organisation": "CPF Plan F",
    "address": "Rue des Guildes 22, 1000 Brussels",
    "telephone": "02 230 04 62",
    "email": "",
    "website": "http://www.planf.be/Horaires",
    "startTime": "2021-07-30T12:00:10.380Z",
    "endTime": "2021-07-30T16:00:10.380Z"
  },
  {
    "place": "Brussels",
    "appointment": "yes",
    "free": "no",
    "day": "Monday",
    "daypart": "morning",
    "hour": "8h15 - 12h",
    "organisation": "CPF Rosa",
    "address": "Rue du Midi 120, 1000 Brussels",
    "telephone": "02 546 14 33",
    "email": "planningrosa@fmsb.be",
    "website": "https://www.planningsfps.be/nos-centres/cpf-bruxelles/",
    "startTime": "2021-07-26T06:15:10.380Z",
    "endTime": "2021-07-26T10:00:10.380Z"
  },
  {
    "place": "Brussels",
    "appointment": "yes",
    "free": "no",
    "day": "Monday",
    "daypart": "afternoon",
    "hour": "12h45 - 16h30",
    "organisation": "CPF Rosa",
    "address": "Rue du Midi 120, 1000 Brussels",
    "telephone": "02 546 14 33",
    "email": "planningrosa@fmsb.be",
    "website": "https://www.planningsfps.be/nos-centres/cpf-bruxelles/",
    "startTime": "2021-07-26T10:45:10.380Z",
    "endTime": "2021-07-26T14:30:10.380Z"
  },
  {
    "place": "Brussels",
    "appointment": "yes",
    "free": "no",
    "day": "Tuesday",
    "daypart": "morning",
    "hour": "8h15 - 12h",
    "organisation": "CPF Rosa",
    "address": "Rue du Midi 120, 1000 Brussels",
    "telephone": "02 546 14 33",
    "email": "planningrosa@fmsb.be",
    "website": "https://www.planningsfps.be/nos-centres/cpf-bruxelles/",
    "startTime": "2021-07-27T06:15:10.380Z",
    "endTime": "2021-07-27T10:00:10.380Z"
  },
  {
    "place": "Brussels",
    "appointment": "yes",
    "free": "no",
    "day": "Tuesday",
    "daypart": "afternoon",
    "hour": "12h45 - 16h30",
    "organisation": "CPF Rosa",
    "address": "Rue du Midi 120, 1000 Brussels",
    "telephone": "02 546 14 33",
    "email": "planningrosa@fmsb.be",
    "website": "https://www.planningsfps.be/nos-centres/cpf-bruxelles/",
    "startTime": "2021-07-27T10:45:10.380Z",
    "endTime": "2021-07-27T14:30:10.380Z"
  },
  {
    "place": "Brussels",
    "appointment": "yes",
    "free": "no",
    "day": "Wednesday",
    "daypart": "morning",
    "hour": "8h15 - 12h",
    "organisation": "CPF Rosa",
    "address": "Rue du Midi 120, 1000 Brussels",
    "telephone": "02 546 14 33",
    "email": "planningrosa@fmsb.be",
    "website": "https://www.planningsfps.be/nos-centres/cpf-bruxelles/",
    "startTime": "2021-07-28T06:15:10.380Z",
    "endTime": "2021-07-28T10:00:10.380Z"
  },
  {
    "place": "Brussels",
    "appointment": "yes",
    "free": "no",
    "day": "Wednesday",
    "daypart": "afternoon",
    "hour": "12h45 - 16h30",
    "organisation": "CPF Rosa",
    "address": "Rue du Midi 120, 1000 Brussels",
    "telephone": "02 546 14 33",
    "email": "planningrosa@fmsb.be",
    "website": "https://www.planningsfps.be/nos-centres/cpf-bruxelles/",
    "startTime": "2021-07-28T10:45:10.380Z",
    "endTime": "2021-07-28T14:30:10.380Z"
  },
  {
    "place": "Brussels",
    "appointment": "yes",
    "free": "no",
    "day": "Thursday",
    "daypart": "morning",
    "hour": "8h15 - 12h",
    "organisation": "CPF Rosa",
    "address": "Rue du Midi 120, 1000 Brussels",
    "telephone": "02 546 14 33",
    "email": "planningrosa@fmsb.be",
    "website": "https://www.planningsfps.be/nos-centres/cpf-bruxelles/",
    "startTime": "2021-07-29T06:15:10.381Z",
    "endTime": "2021-07-29T10:00:10.381Z"
  },
  {
    "place": "Brussels",
    "appointment": "yes",
    "free": "no",
    "day": "Thursday",
    "daypart": "afternoon",
    "hour": "12h45 - 16h30",
    "organisation": "CPF Rosa",
    "address": "Rue du Midi 120, 1000 Brussels",
    "telephone": "02 546 14 33",
    "email": "planningrosa@fmsb.be",
    "website": "https://www.planningsfps.be/nos-centres/cpf-bruxelles/",
    "startTime": "2021-07-29T10:45:10.381Z",
    "endTime": "2021-07-29T14:30:10.381Z"
  },
  {
    "place": "Brussels",
    "appointment": "yes",
    "free": "no",
    "day": "Friday",
    "daypart": "morning",
    "hour": "8h15 - 12h",
    "organisation": "CPF Rosa",
    "address": "Rue du Midi 120, 1000 Brussels",
    "telephone": "02 546 14 33",
    "email": "planningrosa@fmsb.be",
    "website": "https://www.planningsfps.be/nos-centres/cpf-bruxelles/",
    "startTime": "2021-07-30T06:15:10.381Z",
    "endTime": "2021-07-30T10:00:10.381Z"
  },
  {
    "place": "Brussels",
    "appointment": "yes",
    "free": "no",
    "day": "Friday",
    "daypart": "afternoon",
    "hour": "12h45 - 16h30",
    "organisation": "CPF Rosa",
    "address": "Rue du Midi 120, 1000 Brussels",
    "telephone": "02 546 14 33",
    "email": "planningrosa@fmsb.be",
    "website": "https://www.planningsfps.be/nos-centres/cpf-bruxelles/",
    "startTime": "2021-07-30T10:45:10.381Z",
    "endTime": "2021-07-30T14:30:10.381Z"
  },
  {
    "place": "Brussels",
    "appointment": "yes",
    "free": "no",
    "day": "Thursday",
    "daypart": "morning",
    "hour": "9h - 12h",
    "organisation": "CPF Laken",
    "address": "Boulevard Émile Bockstael 91, 1020 Brussels",
    "telephone": "02 325 46 40",
    "email": "laeken@planningfamilial.net",
    "website": "http://www.planninglaeken.be/contact/",
    "startTime": "2021-07-29T07:00:10.381Z",
    "endTime": "2021-07-29T10:00:10.381Z"
  },
  {
    "place": "Brussels",
    "appointment": "yes",
    "free": "no",
    "day": "Friday",
    "daypart": "afternoon",
    "hour": "12h - 18h",
    "organisation": "CPF Laken",
    "address": "Boulevard Émile Bockstael 91, 1020 Brussels",
    "telephone": "02 325 46 40",
    "email": "laeken@planningfamilial.net",
    "website": "http://www.planninglaeken.be/contact/",
    "startTime": "2021-07-30T10:00:10.382Z",
    "endTime": "2021-07-30T16:00:10.382Z"
  },
  {
    "place": "Brussels",
    "appointment": "yes",
    "free": "no",
    "day": "Tuesday",
    "daypart": "morning",
    "hour": "9h - 12h",
    "organisation": "CPF Leman",
    "address": "rue Général Leman 110, 1040 Brussels",
    "telephone": "02 230 10 30",
    "email": "",
    "website": "https://www.guidesocial.be/planningleman/?page=5",
    "startTime": "2021-07-27T07:00:10.382Z",
    "endTime": "2021-07-27T10:00:10.382Z"
  },
  {
    "place": "Brussels",
    "appointment": "yes",
    "free": "no",
    "day": "Tuesday",
    "daypart": "afternoon",
    "hour": "12h30 - 17h",
    "organisation": "CPF Leman",
    "address": "rue Général Leman 110, 1040 Brussels",
    "telephone": "02 230 10 30",
    "email": "",
    "website": "https://www.guidesocial.be/planningleman/?page=6",
    "startTime": "2021-07-27T10:30:10.382Z",
    "endTime": "2021-07-27T15:00:10.382Z"
  },
  {
    "place": "Brussels",
    "appointment": "yes",
    "free": "no",
    "day": "Wednesday",
    "daypart": "afternoon",
    "hour": "13h - 19h",
    "organisation": "CPF Leman",
    "address": "rue Général Leman 110, 1040 Brussels",
    "telephone": "02 230 10 30",
    "email": "",
    "website": "https://www.guidesocial.be/planningleman/?page=7",
    "startTime": "2021-07-28T11:00:10.382Z",
    "endTime": "2021-07-28T17:00:10.382Z"
  },
  {
    "place": "Brussels",
    "appointment": "yes",
    "free": "no",
    "day": "Thursday",
    "daypart": "morning",
    "hour": "9h - 12h",
    "organisation": "CPF Leman",
    "address": "rue Général Leman 110, 1040 Brussels",
    "telephone": "02 230 10 30",
    "email": "",
    "website": "https://www.guidesocial.be/planningleman/?page=8",
    "startTime": "2021-07-29T07:00:10.382Z",
    "endTime": "2021-07-29T10:00:10.382Z"
  },
  {
    "place": "Brussels",
    "appointment": "yes",
    "free": "no",
    "day": "Thursday",
    "daypart": "afternoon",
    "hour": "12h30 - 18h",
    "organisation": "CPF Leman",
    "address": "rue Général Leman 110, 1040 Brussels",
    "telephone": "02 230 10 30",
    "email": "",
    "website": "https://www.guidesocial.be/planningleman/?page=9",
    "startTime": "2021-07-29T10:30:10.382Z",
    "endTime": "2021-07-29T16:00:10.382Z"
  },
  {
    "place": "Brussels",
    "appointment": "yes",
    "free": "no",
    "day": "Friday",
    "daypart": "morning",
    "hour": "9h - 12h",
    "organisation": "CPF Leman",
    "address": "rue Général Leman 110, 1040 Brussels",
    "telephone": "02 230 10 30",
    "email": "",
    "website": "https://www.guidesocial.be/planningleman/?page=10",
    "startTime": "2021-07-30T07:00:10.382Z",
    "endTime": "2021-07-30T10:00:10.382Z"
  },
  {
    "place": "Brussels",
    "appointment": "yes",
    "free": "no",
    "day": "Friday",
    "daypart": "afternoon",
    "hour": "12h30 - 17h",
    "organisation": "CPF Leman",
    "address": "rue Général Leman 110, 1040 Brussels",
    "telephone": "02 230 10 30",
    "email": "",
    "website": "https://www.guidesocial.be/planningleman/?page=11",
    "startTime": "2021-07-30T10:30:10.382Z",
    "endTime": "2021-07-30T15:00:10.383Z"
  },
  {
    "place": "Brussels",
    "appointment": "yes",
    "free": "no",
    "day": "Tuesday",
    "daypart": "afternoon",
    "hour": "13h - 17h",
    "organisation": "Collectif Contraception",
    "address": "Av. des Celtes 50, 1040 Brussels",
    "telephone": "02 736 13 14",
    "email": "",
    "website": "http://collectifcontraception.be/?id=20",
    "startTime": "2021-07-27T11:00:10.383Z",
    "endTime": "2021-07-27T15:00:10.383Z"
  },
  {
    "place": "Brussels",
    "appointment": "yes",
    "free": "no",
    "day": "Wednesday",
    "daypart": "afternoon",
    "hour": "13h30 - 18h30",
    "organisation": "Collectif Contraception",
    "address": "Av. des Celtes 50, 1040 Brussels",
    "telephone": "02 736 13 14",
    "email": "",
    "website": "http://collectifcontraception.be/?id=20",
    "startTime": "2021-07-28T11:30:10.383Z",
    "endTime": "2021-07-28T16:30:10.383Z"
  },
  {
    "place": "Brussels",
    "appointment": "no",
    "free": "no",
    "day": "Wednesday",
    "daypart": "afternoon",
    "hour": "13h30 - 17h30",
    "organisation": "CPF Ixelles",
    "address": "rue du Vivier 89, Brussels",
    "telephone": "02 646 42 73",
    "email": "ixelles.cps@belgacom.net",
    "website": "",
    "startTime": "2021-07-28T11:30:10.383Z",
    "endTime": "2021-07-28T15:30:10.383Z"
  },
  {
    "place": "Brussels",
    "appointment": "yes",
    "free": "no",
    "day": "Monday",
    "daypart": "afternoon",
    "hour": "13h30 - 17h30",
    "organisation": "CPF Ixelles",
    "address": "rue du Vivier 89, Brussels",
    "telephone": "02 646 42 73",
    "email": "ixelles.cps@belgacom.net",
    "website": "",
    "startTime": "2021-07-26T11:30:10.383Z",
    "endTime": "2021-07-26T15:30:10.383Z"
  },
  {
    "place": "Brussels",
    "appointment": "yes",
    "free": "no",
    "day": "Tuesday",
    "daypart": "afternoon",
    "hour": "13h30 - 17h30",
    "organisation": "CPF Ixelles",
    "address": "rue du Vivier 89, Brussels",
    "telephone": "02 646 42 73",
    "email": "ixelles.cps@belgacom.net",
    "website": "",
    "startTime": "2021-07-27T11:30:10.383Z",
    "endTime": "2021-07-27T15:30:10.383Z"
  },
  {
    "place": "Brussels",
    "appointment": "yes",
    "free": "no",
    "day": "Thursday",
    "daypart": "afternoon",
    "hour": "13h30 - 17h30",
    "organisation": "CPF Ixelles",
    "address": "rue du Vivier 89, Brussels",
    "telephone": "02 646 42 73",
    "email": "ixelles.cps@belgacom.net",
    "website": "",
    "startTime": "2021-07-29T11:30:10.383Z",
    "endTime": "2021-07-29T15:30:10.383Z"
  },
  {
    "place": "Brussels",
    "appointment": "yes",
    "free": "no",
    "day": "Friday",
    "daypart": "afternoon",
    "hour": "13h30 - 17h30",
    "organisation": "CPF Ixelles",
    "address": "rue du Vivier 89, Brussels",
    "telephone": "02 646 42 73",
    "email": "ixelles.cps@belgacom.net",
    "website": "",
    "startTime": "2021-07-30T11:30:10.383Z",
    "endTime": "2021-07-30T15:30:10.383Z"
  },
  {
    "place": "Brussels",
    "appointment": "yes",
    "free": "no",
    "day": "Monday",
    "daypart": "morning",
    "hour": "9h - 12h",
    "organisation": "Aimer à L’ULB",
    "address": "Avenue Jeanne 38, Brussels",
    "telephone": "02 650 31 31",
    "email": "",
    "website": "http://www.aimeralulb.be/",
    "startTime": "2021-07-26T07:00:10.383Z",
    "endTime": "2021-07-26T10:00:10.383Z"
  },
  {
    "place": "Brussels",
    "appointment": "yes",
    "free": "no",
    "day": "Monday",
    "daypart": "afternoon",
    "hour": "12h30 - 19h",
    "organisation": "aimer à L’ULB",
    "address": "Avenue Jeanne 38, Brussels",
    "telephone": "02 650 31 31",
    "email": "",
    "website": "http://www.aimeralulb.be/",
    "startTime": "2021-07-26T10:30:10.384Z",
    "endTime": "2021-07-26T17:00:10.384Z"
  },
  {
    "place": "Brussels",
    "appointment": "yes",
    "free": "no",
    "day": "Tuesday",
    "daypart": "morning",
    "hour": "9h - 12h",
    "organisation": "Aimer à L’ULB",
    "address": "Avenue Jeanne 38, Brussels",
    "telephone": "02 650 31 31",
    "email": "",
    "website": "http://www.aimeralulb.be/",
    "startTime": "2021-07-27T07:00:10.384Z",
    "endTime": "2021-07-27T10:00:10.384Z"
  },
  {
    "place": "Brussels",
    "appointment": "yes",
    "free": "no",
    "day": "Tuesday",
    "daypart": "afternoon",
    "hour": "12h30 - 19h",
    "organisation": "aimer à L’ULB",
    "address": "Avenue Jeanne 38, Brussels",
    "telephone": "02 650 31 31",
    "email": "",
    "website": "http://www.aimeralulb.be/",
    "startTime": "2021-07-27T10:30:10.384Z",
    "endTime": "2021-07-27T17:00:10.384Z"
  },
  {
    "place": "Brussels",
    "appointment": "yes",
    "free": "no",
    "day": "Wednesday",
    "daypart": "morning",
    "hour": "9h - 12h",
    "organisation": "Aimer à L’ULB",
    "address": "Avenue Jeanne 38, Brussels",
    "telephone": "02 650 31 31",
    "email": "",
    "website": "http://www.aimeralulb.be/",
    "startTime": "2021-07-28T07:00:10.384Z",
    "endTime": "2021-07-28T10:00:10.384Z"
  },
  {
    "place": "Brussels",
    "appointment": "yes",
    "free": "no",
    "day": "Wednesday",
    "daypart": "afternoon",
    "hour": "12h30 - 19h",
    "organisation": "aimer à L’ULB",
    "address": "Avenue Jeanne 38, Brussels",
    "telephone": "02 650 31 31",
    "email": "",
    "website": "http://www.aimeralulb.be/",
    "startTime": "2021-07-28T10:30:10.384Z",
    "endTime": "2021-07-28T17:00:10.384Z"
  },
  {
    "place": "Brussels",
    "appointment": "yes",
    "free": "no",
    "day": "Thursday",
    "daypart": "morning",
    "hour": "9h - 12h",
    "organisation": "Aimer à L’ULB",
    "address": "Avenue Jeanne 38, Brussels",
    "telephone": "02 650 31 31",
    "email": "",
    "website": "http://www.aimeralulb.be/",
    "startTime": "2021-07-29T07:00:10.384Z",
    "endTime": "2021-07-29T10:00:10.384Z"
  },
  {
    "place": "Brussels",
    "appointment": "yes",
    "free": "no",
    "day": "Thursday",
    "daypart": "afternoon",
    "hour": "12h30 - 19h",
    "organisation": "aimer à L’ULB",
    "address": "Avenue Jeanne 38, Brussels",
    "telephone": "02 650 31 31",
    "email": "",
    "website": "http://www.aimeralulb.be/",
    "startTime": "2021-07-29T10:30:10.384Z",
    "endTime": "2021-07-29T17:00:10.384Z"
  },
  {
    "place": "Brussels",
    "appointment": "yes",
    "free": "no",
    "day": "Friday",
    "daypart": "morning",
    "hour": "9h - 12h",
    "organisation": "Aimer à L’ULB",
    "address": "Avenue Jeanne 38, Brussels",
    "telephone": "02 650 31 31",
    "email": "",
    "website": "http://www.aimeralulb.be/",
    "startTime": "2021-07-30T07:00:10.385Z",
    "endTime": "2021-07-30T10:00:10.385Z"
  },
  {
    "place": "Brussels",
    "appointment": "yes",
    "free": "no",
    "day": "Friday",
    "daypart": "afternoon",
    "hour": "12h30 - 19h",
    "organisation": "aimer à L’ULB",
    "address": "Avenue Jeanne 38, Brussels",
    "telephone": "02 650 31 31",
    "email": "",
    "website": "http://www.aimeralulb.be/",
    "startTime": "2021-07-30T10:30:10.385Z",
    "endTime": "2021-07-30T17:00:10.385Z"
  },
  {
    "place": "Brussels",
    "appointment": "yes",
    "free": "no",
    "day": "Saturday",
    "daypart": "morning",
    "hour": "9h30 - 12h30",
    "organisation": "Aimer à L’ULB",
    "address": "Avenue Jeanne 38, Brussels",
    "telephone": "02 650 31 31",
    "email": "",
    "website": "http://www.aimeralulb.be/",
    "startTime": "2021-07-31T07:30:10.385Z",
    "endTime": "2021-07-31T10:30:10.385Z"
  },
  {
    "place": "Brussels",
    "appointment": "yes",
    "free": "no",
    "day": "Monday",
    "daypart": "morning",
    "hour": "9h - 11h40",
    "organisation": "CPF Saint-Gilles",
    "address": "Avenue du Parc 89, 1060 Brussels",
    "telephone": "02 537 11 08",
    "email": "",
    "website": "https://www.planningfamilialstgilles.be/infos-pratiques",
    "startTime": "2021-07-26T07:00:10.385Z",
    "endTime": "2021-07-26T09:40:10.385Z"
  },
  {
    "place": "Brussels",
    "appointment": "yes",
    "free": "no",
    "day": "Monday",
    "daypart": "afternoon",
    "hour": "14h30 - 14h30",
    "organisation": "CPF Saint-Gilles",
    "address": "Avenue du Parc 89, 1060 Brussels",
    "telephone": "02 537 11 08",
    "email": "",
    "website": "https://www.planningfamilialstgilles.be/infos-pratiques",
    "startTime": "2021-07-26T12:30:10.385Z",
    "endTime": "2021-07-26T12:30:10.385Z"
  },
  {
    "place": "Brussels",
    "appointment": "yes",
    "free": "no",
    "day": "Tuesday",
    "daypart": "morning",
    "hour": "9h - 12h",
    "organisation": "CPF Saint-Gilles",
    "address": "Avenue du Parc 89, 1060 Brussels",
    "telephone": "02 537 11 08",
    "email": "",
    "website": "https://www.planningfamilialstgilles.be/infos-pratiques",
    "startTime": "2021-07-27T07:00:10.385Z",
    "endTime": "2021-07-27T10:00:10.385Z"
  },
  {
    "place": "Brussels",
    "appointment": "yes",
    "free": "no",
    "day": "Tuesday",
    "daypart": "afternoon",
    "hour": "13h30 - 17h",
    "organisation": "CPF Saint-Gilles",
    "address": "Avenue du Parc 89, 1060 Brussels",
    "telephone": "02 537 11 08",
    "email": "",
    "website": "https://www.planningfamilialstgilles.be/infos-pratiques",
    "startTime": "2021-07-27T11:30:10.385Z",
    "endTime": "2021-07-27T15:00:10.385Z"
  },
  {
    "place": "Brussels",
    "appointment": "yes",
    "free": "no",
    "day": "Wednesday",
    "daypart": "morning",
    "hour": "9h - 12h",
    "organisation": "CPF Saint-Gilles",
    "address": "Avenue du Parc 89, 1060 Brussels",
    "telephone": "02 537 11 08",
    "email": "",
    "website": "https://www.planningfamilialstgilles.be/infos-pratiques",
    "startTime": "2021-07-28T07:00:10.385Z",
    "endTime": "2021-07-28T10:00:10.385Z"
  },
  {
    "place": "Brussels",
    "appointment": "yes",
    "free": "no",
    "day": "Wednesday",
    "daypart": "afternoon",
    "hour": "13h30 - 16h",
    "organisation": "CPF Saint-Gilles",
    "address": "Avenue du Parc 89, 1060 Brussels",
    "telephone": "02 537 11 08",
    "email": "",
    "website": "https://www.planningfamilialstgilles.be/infos-pratiques",
    "startTime": "2021-07-28T11:30:10.386Z",
    "endTime": "2021-07-28T14:00:10.386Z"
  },
  {
    "place": "Brussels",
    "appointment": "yes",
    "free": "no",
    "day": "Friday",
    "daypart": "afternoon",
    "hour": "14h30 - 16h30",
    "organisation": "CPF Saint-Gilles",
    "address": "Avenue du Parc 89, 1060 Brussels",
    "telephone": "02 537 11 08",
    "email": "",
    "website": "https://www.planningfamilialstgilles.be/infos-pratiques",
    "startTime": "2021-07-30T12:30:10.386Z",
    "endTime": "2021-07-30T14:30:10.386Z"
  },
  {
    "place": "Brussels",
    "appointment": "yes",
    "free": "no",
    "day": "Wednesday",
    "daypart": "afternoon",
    "hour": "13h - 18h",
    "organisation": "CPF Midi",
    "address": "Avenue Clemenceau 23, 1070 Bruxelles",
    "telephone": "02 511 38 38",
    "email": "accueil@cpfmidi.be",
    "website": "https://www.cpfmidi.be/consultations-medicales/",
    "startTime": "2021-07-28T11:00:10.386Z",
    "endTime": "2021-07-28T16:00:10.386Z"
  },
  {
    "place": "Brussels",
    "appointment": "yes",
    "free": "no",
    "day": "Monday",
    "daypart": "afternoon",
    "hour": "12h30 - 18h",
    "organisation": "CPF Séverine",
    "address": "Raymond Vander Bruggen 84, 1070 Brussels",
    "telephone": "02 524 33 14",
    "email": "info@planning-severine.org",
    "website": "https://www.planning-severine.org/nos-services",
    "startTime": "2021-07-26T10:30:10.386Z",
    "endTime": "2021-07-26T16:00:10.386Z"
  },
  {
    "place": "Brussels",
    "appointment": "yes",
    "free": "no",
    "day": "Tuesday",
    "daypart": "afternoon",
    "hour": "12h30 - 18h",
    "organisation": "CPF Séverine",
    "address": "Raymond Vander Bruggen 84, 1070 Brussels",
    "telephone": "02 524 33 14",
    "email": "info@planning-severine.org",
    "website": "https://www.planning-severine.org/nos-services",
    "startTime": "2021-07-27T10:30:10.386Z",
    "endTime": "2021-07-27T16:00:10.386Z"
  },
  {
    "place": "Brussels",
    "appointment": "yes",
    "free": "no",
    "day": "Thursday",
    "daypart": "afternoon",
    "hour": "12h30 - 18h30",
    "organisation": "CPF Séverine",
    "address": "Raymond Vander Bruggen 84, 1070 Brussels",
    "telephone": "02 524 33 14",
    "email": "info@planning-severine.org",
    "website": "https://www.planning-severine.org/nos-services",
    "startTime": "2021-07-29T10:30:10.386Z",
    "endTime": "2021-07-29T16:30:10.386Z"
  },
  {
    "place": "Brussels",
    "appointment": "yes",
    "free": "no",
    "day": "Friday",
    "daypart": "morning",
    "hour": "9h - 13h30",
    "organisation": "CPF Séverine",
    "address": "Raymond Vander Bruggen 84, 1070 Brussels",
    "telephone": "02 524 33 14",
    "email": "info@planning-severine.org",
    "website": "https://www.planning-severine.org/nos-services",
    "startTime": "2021-07-30T07:00:10.386Z",
    "endTime": "2021-07-30T11:30:10.387Z"
  },
  {
    "place": "Brussels",
    "appointment": "yes",
    "free": "no",
    "day": "Friday",
    "daypart": "afternoon",
    "hour": "16h - 17h30",
    "organisation": "CPF Séverine",
    "address": "Raymond Vander Bruggen 84, 1070 Brussels",
    "telephone": "02 524 33 14",
    "email": "info@planning-severine.org",
    "website": "https://www.planning-severine.org/nos-services",
    "startTime": "2021-07-30T14:00:10.387Z",
    "endTime": "2021-07-30T15:30:10.387Z"
  },
  {
    "place": "Brussels",
    "appointment": "yes",
    "free": "no",
    "day": "Monday",
    "daypart": "afternoon",
    "hour": "16h - 17h",
    "organisation": "CPF Evere",
    "address": "rue Adolphe De Brandt 70 , 1140 Brussels",
    "telephone": "02 216 20 04",
    "email": "planning.familial.evere@brutele.be",
    "website": "http://www.lentrela.be/-Planning-Familial-d-Evere-127-",
    "startTime": "2021-07-26T14:00:10.387Z",
    "endTime": "2021-07-26T15:00:10.388Z"
  },
  {
    "place": "Brussels",
    "appointment": "no",
    "free": "no",
    "day": "Monday",
    "daypart": "afternoon",
    "hour": "17h - 18h",
    "organisation": "CPF Evere",
    "address": "rue Adolphe De Brandt 70 , 1140 Brussels",
    "telephone": "02 216 20 04",
    "email": "planning.familial.evere@brutele.be",
    "website": "http://www.lentrela.be/-Planning-Familial-d-Evere-127-",
    "startTime": "2021-07-26T15:00:10.388Z",
    "endTime": "2021-07-26T16:00:10.388Z"
  },
  {
    "place": "Brussels",
    "appointment": "yes",
    "free": "no",
    "day": "Wednesday",
    "daypart": "afternoon",
    "hour": "14h - 16h",
    "organisation": "CPF Evere",
    "address": "rue Adolphe De Brandt 70 , 1140 Brussels",
    "telephone": "02 216 20 04",
    "email": "planning.familial.evere@brutele.be",
    "website": "http://www.lentrela.be/-Planning-Familial-d-Evere-127-",
    "startTime": "2021-07-28T12:00:10.388Z",
    "endTime": "2021-07-28T14:00:10.388Z"
  },
  {
    "place": "Brussels",
    "appointment": "yes",
    "free": "no",
    "day": "Wednesday",
    "daypart": "afternoon",
    "hour": "16h - 17h",
    "organisation": "CPF Evere",
    "address": "rue Adolphe De Brandt 70 , 1140 Brussels",
    "telephone": "02 216 20 04",
    "email": "planning.familial.evere@brutele.be",
    "website": "http://www.lentrela.be/-Planning-Familial-d-Evere-127-",
    "startTime": "2021-07-28T14:00:10.388Z",
    "endTime": "2021-07-28T15:00:10.388Z"
  },
  {
    "place": "Brussels",
    "appointment": "yes",
    "free": "no",
    "day": "Monday",
    "daypart": "morning",
    "hour": "10h - 12h",
    "organisation": "CPF Woluwé-St-Pierre",
    "address": "Rue Jean Deraeck 14, 1150 Brussels",
    "telephone": "02 762 00 67",
    "email": "",
    "website": "https://www.guidesocial.be/planningwoluwe/?page=5",
    "startTime": "2021-07-26T08:00:10.388Z",
    "endTime": "2021-07-26T10:00:10.388Z"
  },
  {
    "place": "Brussels",
    "appointment": "yes",
    "free": "no",
    "day": "Monday",
    "daypart": "afternoon",
    "hour": "13h - 18h",
    "organisation": "CPF Woluwé-St-Pierre",
    "address": "Rue Jean Deraeck 14, 1150 Brussels",
    "telephone": "02 762 00 67",
    "email": "",
    "website": "https://www.guidesocial.be/planningwoluwe/?page=6",
    "startTime": "2021-07-26T11:00:10.388Z",
    "endTime": "2021-07-26T16:00:10.388Z"
  },
  {
    "place": "Brussels",
    "appointment": "yes",
    "free": "no",
    "day": "Tuesday",
    "daypart": "afternoon",
    "hour": "14h - 18h",
    "organisation": "CPF Woluwé-St-Pierre",
    "address": "Rue Jean Deraeck 14, 1150 Brussels",
    "telephone": "02 762 00 67",
    "email": "",
    "website": "https://www.guidesocial.be/planningwoluwe/?page=8",
    "startTime": "2021-07-27T12:00:10.388Z",
    "endTime": "2021-07-27T16:00:10.388Z"
  },
  {
    "place": "Brussels",
    "appointment": "yes",
    "free": "no",
    "day": "Wednesday",
    "daypart": "afternoon",
    "hour": "13h - 18h",
    "organisation": "CPF Woluwé-St-Pierre",
    "address": "Rue Jean Deraeck 14, 1150 Brussels",
    "telephone": "02 762 00 67",
    "email": "",
    "website": "https://www.guidesocial.be/planningwoluwe/?page=9",
    "startTime": "2021-07-28T11:00:10.388Z",
    "endTime": "2021-07-28T16:00:10.388Z"
  },
  {
    "place": "Brussels",
    "appointment": "yes",
    "free": "no",
    "day": "Thursday",
    "daypart": "afternoon",
    "hour": "12h30 - 17h30",
    "organisation": "CPF Woluwé-St-Pierre",
    "address": "Rue Jean Deraeck 14, 1150 Brussels",
    "telephone": "02 762 00 67",
    "email": "",
    "website": "https://www.guidesocial.be/planningwoluwe/?page=10",
    "startTime": "2021-07-29T10:30:10.388Z",
    "endTime": "2021-07-29T15:30:10.388Z"
  },
  {
    "place": "Brussels",
    "appointment": "yes",
    "free": "no",
    "day": "Friday",
    "daypart": "morning",
    "hour": "10h - 12h",
    "organisation": "CPF Woluwé-St-Pierre",
    "address": "Rue Jean Deraeck 14, 1150 Brussels",
    "telephone": "02 762 00 67",
    "email": "",
    "website": "https://www.guidesocial.be/planningwoluwe/?page=11",
    "startTime": "2021-07-30T08:00:10.388Z",
    "endTime": "2021-07-30T10:00:10.389Z"
  },
  {
    "place": "Brussels",
    "appointment": "yes",
    "free": "no",
    "day": "Friday",
    "daypart": "afternoon",
    "hour": "13h - 17h30",
    "organisation": "CPF Woluwé-St-Pierre",
    "address": "Rue Jean Deraeck 14, 1150 Brussels",
    "telephone": "02 762 00 67",
    "email": "",
    "website": "https://www.guidesocial.be/planningwoluwe/?page=12",
    "startTime": "2021-07-30T11:00:10.389Z",
    "endTime": "2021-07-30T15:30:10.389Z"
  },
  {
    "place": "Brussels",
    "appointment": "yes",
    "free": "no",
    "day": "Tuesday",
    "daypart": "afternoon",
    "hour": "15h30 - 18h",
    "organisation": "CPF Woluwé-Saint-Lambert CCFS",
    "address": "Avenue de Broqueville 270, 1200 Brussels",
    "telephone": "02 736 41 50",
    "email": "ccfs@skynet.be",
    "website": "http://www.planning-familial-wsl.be/index.php/infos-generales/horaires/medicales",
    "startTime": "2021-07-27T13:30:10.389Z",
    "endTime": "2021-07-27T16:00:10.389Z"
  },
  {
    "place": "Brussels",
    "appointment": "yes",
    "free": "no",
    "day": "Wednesday",
    "daypart": "afternoon",
    "hour": "13h30 - 18h30",
    "organisation": "CPF Woluwé-Saint-Lambert CCFS",
    "address": "Avenue de Broqueville 270, 1200 Brussels",
    "telephone": "02 736 41 50",
    "email": "ccfs@skynet.be",
    "website": "http://www.planning-familial-wsl.be/index.php/infos-generales/horaires/medicales",
    "startTime": "2021-07-28T11:30:10.389Z",
    "endTime": "2021-07-28T16:30:10.389Z"
  },
  {
    "place": "Brussels",
    "appointment": "yes",
    "free": "no",
    "day": "Thursday",
    "daypart": "afternoon",
    "hour": "15h30 - 18h",
    "organisation": "CPF Woluwé-Saint-Lambert CCFS",
    "address": "Avenue de Broqueville 270, 1200 Brussels",
    "telephone": "02 736 41 50",
    "email": "ccfs@skynet.be",
    "website": "http://www.planning-familial-wsl.be/index.php/infos-generales/horaires/medicales",
    "startTime": "2021-07-29T13:30:10.389Z",
    "endTime": "2021-07-29T16:00:10.389Z"
  },
  {
    "place": "Brussels",
    "appointment": "yes",
    "free": "no",
    "day": "Monday",
    "daypart": "morning",
    "hour": "9h - 12h",
    "organisation": "CPF Saint-Josse",
    "address": "Place Quetelet 4, 1210 Brussels",
    "telephone": "02 217 44 50",
    "email": "",
    "website": "https://www.planningsaintjosse.com/les-i-s-t",
    "startTime": "2021-07-26T07:00:10.389Z",
    "endTime": "2021-07-26T10:00:10.390Z"
  },
  {
    "place": "Brussels",
    "appointment": "yes",
    "free": "no",
    "day": "Monday",
    "daypart": "afternoon",
    "hour": "13h - 18h",
    "organisation": "CPF Saint-Josse",
    "address": "Place Quetelet 4, 1210 Brussels",
    "telephone": "02 217 44 50",
    "email": "",
    "website": "https://www.planningsaintjosse.com/les-i-s-t",
    "startTime": "2021-07-26T11:00:10.390Z",
    "endTime": "2021-07-26T16:00:10.390Z"
  },
  {
    "place": "Brussels",
    "appointment": "yes",
    "free": "no",
    "day": "Tuesday",
    "daypart": "morning",
    "hour": "9h - 12h",
    "organisation": "CPF Saint-Josse",
    "address": "Place Quetelet 4, 1210 Brussels",
    "telephone": "02 217 44 50",
    "email": "",
    "website": "https://www.planningsaintjosse.com/les-i-s-t",
    "startTime": "2021-07-27T07:00:10.390Z",
    "endTime": "2021-07-27T10:00:10.390Z"
  },
  {
    "place": "Brussels",
    "appointment": "yes",
    "free": "no",
    "day": "Tuesday",
    "daypart": "afternoon",
    "hour": "14h - 18h",
    "organisation": "CPF Saint-Josse",
    "address": "Place Quetelet 4, 1210 Brussels",
    "telephone": "02 217 44 50",
    "email": "",
    "website": "https://www.planningsaintjosse.com/les-i-s-t",
    "startTime": "2021-07-27T12:00:10.390Z",
    "endTime": "2021-07-27T16:00:10.390Z"
  },
  {
    "place": "Brussels",
    "appointment": "yes",
    "free": "no",
    "day": "Wednesday",
    "daypart": "morning",
    "hour": "9h - 12h",
    "organisation": "CPF Saint-Josse",
    "address": "Place Quetelet 4, 1210 Brussels",
    "telephone": "02 217 44 50",
    "email": "",
    "website": "https://www.planningsaintjosse.com/les-i-s-t",
    "startTime": "2021-07-28T07:00:10.390Z",
    "endTime": "2021-07-28T10:00:10.391Z"
  },
  {
    "place": "Brussels",
    "appointment": "yes",
    "free": "no",
    "day": "Wednesday",
    "daypart": "afternoon",
    "hour": "13h - 18h",
    "organisation": "CPF Saint-Josse",
    "address": "Place Quetelet 4, 1210 Brussels",
    "telephone": "02 217 44 50",
    "email": "",
    "website": "https://www.planningsaintjosse.com/les-i-s-t",
    "startTime": "2021-07-28T11:00:10.392Z",
    "endTime": "2021-07-28T16:00:10.392Z"
  },
  {
    "place": "Brussels",
    "appointment": "yes",
    "free": "no",
    "day": "Thursday",
    "daypart": "morning",
    "hour": "9h - 12h",
    "organisation": "CPF Saint-Josse",
    "address": "Place Quetelet 4, 1210 Brussels",
    "telephone": "02 217 44 50",
    "email": "",
    "website": "https://www.planningsaintjosse.com/les-i-s-t",
    "startTime": "2021-07-29T07:00:10.392Z",
    "endTime": "2021-07-29T10:00:10.392Z"
  },
  {
    "place": "Brussels",
    "appointment": "yes",
    "free": "no",
    "day": "Thursday",
    "daypart": "afternoon",
    "hour": "13h - 18h",
    "organisation": "CPF Saint-Josse",
    "address": "Place Quetelet 4, 1210 Brussels",
    "telephone": "02 217 44 50",
    "email": "",
    "website": "https://www.planningsaintjosse.com/les-i-s-t",
    "startTime": "2021-07-29T11:00:10.392Z",
    "endTime": "2021-07-29T16:00:10.392Z"
  },
  {
    "place": "Brussels",
    "appointment": "yes",
    "free": "no",
    "day": "Friday",
    "daypart": "morning",
    "hour": "9h - 12h",
    "organisation": "CPF Saint-Josse",
    "address": "Place Quetelet 4, 1210 Brussels",
    "telephone": "02 217 44 50",
    "email": "",
    "website": "https://www.planningsaintjosse.com/les-i-s-t",
    "startTime": "2021-07-30T07:00:10.392Z",
    "endTime": "2021-07-30T10:00:10.392Z"
  },
  {
    "place": "Brussels",
    "appointment": "yes",
    "free": "no",
    "day": "Friday",
    "daypart": "afternoon",
    "hour": "13h - 17h",
    "organisation": "CPF Saint-Josse",
    "address": "Place Quetelet 4, 1210 Brussels",
    "telephone": "02 217 44 50",
    "email": "",
    "website": "https://www.planningsaintjosse.com/les-i-s-t",
    "startTime": "2021-07-30T11:00:10.392Z",
    "endTime": "2021-07-30T15:00:10.392Z"
  },
  {
    "place": "Brussels",
    "appointment": "yes",
    "free": "no",
    "day": "Wednesday",
    "daypart": "afternoon",
    "hour": "16h45 - 18h30",
    "organisation": "CPF Bureaux de Quartiers",
    "address": "Rue du Noyer 344,1030 Bruxelles",
    "telephone": "02 733 43 95",
    "email": "",
    "website": "http://www.bureauxdequartiers.be/",
    "startTime": "2021-07-28T14:45:10.392Z",
    "endTime": "2021-07-28T16:30:10.392Z"
  },
  {
    "place": "Brussels",
    "appointment": "yes",
    "free": "no",
    "day": "Thursday",
    "daypart": "afternoon",
    "hour": "16h00 - 17h45",
    "organisation": "CPF Bureaux de Quartiers",
    "address": "Rue du Noyer 344,1030 Bruxelles",
    "telephone": "02 733 43 95",
    "email": "",
    "website": "http://www.bureauxdequartiers.be/",
    "startTime": "2021-07-29T14:00:10.392Z",
    "endTime": "2021-07-29T15:45:10.392Z"
  },
  {
    "place": "Brussels",
    "appointment": "yes",
    "free": "no",
    "day": "Friday",
    "daypart": "afternoon",
    "hour": "15h00 - 16h45",
    "organisation": "CPF Bureaux de Quartiers",
    "address": "Rue du Noyer 344,1030 Bruxelles",
    "telephone": "02 733 43 95",
    "email": "",
    "website": "http://www.bureauxdequartiers.be/",
    "startTime": "2021-07-30T13:00:10.392Z",
    "endTime": "2021-07-30T14:45:10.393Z"
  },
  {
    "place": "Brussels",
    "appointment": "no",
    "free": "yes",
    "day": "Wednesday",
    "daypart": "afternoon",
    "hour": "15h30 - 17H30 (only subsaharan africans)",
    "organisation": "Plate-Forme Prévention Sida",
    "address": "rue du Champ de Mars 5, 1050 Brussels",
    "telephone": "",
    "email": "",
    "website": "",
    "startTime": "2021-07-28T13:30:10.393Z",
    "endTime": "2021-07-28T15:14:10.393Z"
  },
  {
    "place": "I'm a sexworker",
    "appointment": "no",
    "free": "yes",
    "day": "Tuesday",
    "daypart": "afternoon",
    "hour": "19h - 20h",
    "organisation": "Espace P",
    "address": "rue des Plantes 116, 1030 Brussels",
    "telephone": "02 219 98 74",
    "email": "bruxelles@espacep.be",
    "website": "http://espacep.be/contact/bruxelles/",
    "startTime": "2021-07-27T17:00:10.393Z",
    "endTime": "2021-07-27T18:00:10.393Z"
  },
  {
    "place": "I'm a sexworker",
    "appointment": "no",
    "free": "yes",
    "day": "Wednesday",
    "daypart": "afternoon",
    "hour": "13h - 14h",
    "organisation": "Espace P",
    "address": "rue des Plantes 116, 1030 Brussels",
    "telephone": "02 219 98 74",
    "email": "bruxelles@espacep.be",
    "website": "http://espacep.be/contact/bruxelles/",
    "startTime": "2021-07-28T11:00:10.393Z",
    "endTime": "2021-07-28T12:00:10.393Z"
  }
]